[{"avtale_eier":"Institutt for geografi","utvprogramkode":"ERASMUS+","avtaleid":"1009","eksternt_sted":"University of Manchester","landnavn_norsk":"Storbritannia og Nord-Irland","landnavn_engelsk":"United Kingdom","fagnavn_norsk":"Geografi","studietypenr":7984}
,{"avtale_eier":"Institutt for sammenliknende politikk","utvprogramkode":"ERASMUS+","avtaleid":"1031","eksternt_sted":"Scuola Normale Superiore","landnavn_norsk":"Italia","landnavn_engelsk":"Italy","fagnavn_norsk":"Sammenliknende politikk","studietypenr":7994}
,{"avtale_eier":"Universitetet i Bergen","utvprogramkode":"BILATERAL","avtaleid":"1046","eksternt_sted":"Universidade de São Paulo","landnavn_norsk":"Brasil","landnavn_engelsk":"Brazil","fagnavn_norsk":"Alle fag","studietypenr":8004}
,{"avtale_eier":"Institutt for sammenliknende politikk","utvprogramkode":"ERASMUS+","avtaleid":"108-2","eksternt_sted":"Ollscoil Luimnigh","landnavn_norsk":"Irland","landnavn_engelsk":"Ireland","fagnavn_norsk":"Statsvitenskap"}
,{"avtale_eier":"Universitetet i Bergen","utvprogramkode":"BILATERAL","avtaleid":"1081-1","eksternt_sted":"Zhejiang University","landnavn_norsk":"Kina","landnavn_engelsk":"China","studietypenr":8274}
,{"avtale_eier":"Institutt for sammenliknende politikk","utvprogramkode":"ERASMUS+","avtaleid":"109-7","eksternt_sted":"Universiteit van Amsterdam","landnavn_norsk":"Nederland","landnavn_engelsk":"Netherlands","fagnavn_norsk":"Statsvitenskap","studietypenr":7832}
,{"avtale_eier":"Institutt for sosialantropologi","utvprogramkode":"ERASMUS+","avtaleid":"109-8","eksternt_sted":"Universiteit van Amsterdam","landnavn_norsk":"Nederland","landnavn_engelsk":"Netherlands","fagnavn_norsk":"Sosialantropologi","studietypenr":7831}
,{"avtale_eier":"Institutt for administrasjon og organisasjonsvitenskap","utvprogramkode":"ERASMUS+","avtaleid":"113-4","eksternt_sted":"Universiteit Leiden","landnavn_norsk":"Nederland","landnavn_engelsk":"Netherlands","fagnavn_norsk":"Administrasjon og organisasjonsvitenskap","studietypenr":7879}
,{"avtale_eier":"Institutt for sosialantropologi","utvprogramkode":"ERASMUS+","avtaleid":"114-5","eksternt_sted":"Radboud Universiteit","landnavn_norsk":"Nederland","landnavn_engelsk":"Netherlands","fagnavn_norsk":"Sosialantropologi","studietypenr":7058}
,{"avtale_eier":"Institutt for økonomi","utvprogramkode":"ERASMUS+","avtaleid":"115-4","eksternt_sted":"Erasmus Universiteit Rotterdam","landnavn_norsk":"Nederland","landnavn_engelsk":"Netherlands","fagnavn_norsk":"Økonomi","studietypenr":7546}
,{"avtale_eier":"Institutt for geografi","utvprogramkode":"ERASMUS+","avtaleid":"116-4","eksternt_sted":"Universiteit Utrecht","landnavn_norsk":"Nederland","landnavn_engelsk":"Netherlands","fagnavn_norsk":"Geografi","studietypenr":7549}
,{"avtale_eier":"Institutt for sammenliknende politikk","utvprogramkode":"ERASMUS+","avtaleid":"1168","eksternt_sted":"Institut d'études politiques de Lille","landnavn_norsk":"Frankrike","landnavn_engelsk":"France","fagnavn_norsk":"Sammenliknende politikk","studietypenr":8031}
,{"avtale_eier":"Institutt for administrasjon og organisasjonsvitenskap","utvprogramkode":"ERASMUS+","avtaleid":"1168-1","eksternt_sted":"Institut d'études politiques de Lille","landnavn_norsk":"Frankrike","landnavn_engelsk":"France","fagnavn_norsk":"Administrasjon og organisasjonsvitenskap"}
,{"avtale_eier":"Institutt for sammenliknende politikk","utvprogramkode":"ERASMUS+","avtaleid":"1181","eksternt_sted":"Istanbul Teknik Üniversitesi","landnavn_norsk":"Tyrkia","landnavn_engelsk":"Turkey","fagnavn_norsk":"Sammenliknende politikk"}
,{"avtale_eier":"Universitetet i Bergen","utvprogramkode":"ERASMUS+","avtaleid":"1233","eksternt_sted":"Háskólinn í Reykjavík","landnavn_norsk":"Island","landnavn_engelsk":"Iceland","fagnavn_norsk":"Alle fag","studietypenr":8151}
,{"avtale_eier":"Institutt for økonomi","utvprogramkode":"ERASMUS+","avtaleid":"1233-2","eksternt_sted":"Háskólinn í Reykjavík","landnavn_norsk":"Island","landnavn_engelsk":"Iceland","fagnavn_norsk":"Økonomi"}
,{"avtale_eier":"Institutt for sammenliknende politikk","utvprogramkode":"ERASMUS+","avtaleid":"1245","eksternt_sted":"Sciences Po Toulouse","landnavn_norsk":"Frankrike","landnavn_engelsk":"France","fagnavn_norsk":"Sammenliknende politikk","studietypenr":8293}
,{"avtale_eier":"Institutt for sammenliknende politikk","utvprogramkode":"ERASMUS+","avtaleid":"139-5","eksternt_sted":"University of Warwick","landnavn_norsk":"Storbritannia og Nord-Irland","landnavn_engelsk":"United Kingdom","fagnavn_norsk":"Statsvitenskap","studietypenr":7842}
,{"avtale_eier":"Institutt for geografi","utvprogramkode":"ERASMUS+","avtaleid":"142-4","eksternt_sted":"University of Glasgow","landnavn_norsk":"Storbritannia og Nord-Irland","landnavn_engelsk":"United Kingdom","fagnavn_norsk":"Geografi","studietypenr":7457}
,{"avtale_eier":"Sosiologisk institutt","utvprogramkode":"ERASMUS+","avtaleid":"142-5","eksternt_sted":"University of Glasgow","landnavn_norsk":"Storbritannia og Nord-Irland","landnavn_engelsk":"United Kingdom","fagnavn_norsk":"Sosiologi","studietypenr":7861}
,{"avtale_eier":"Sosiologisk institutt","utvprogramkode":"ERASMUS+","avtaleid":"146-3","eksternt_sted":"Loughborough University","landnavn_norsk":"Storbritannia og Nord-Irland","landnavn_engelsk":"United Kingdom","fagnavn_norsk":"Sosiologi","studietypenr":7459}
,{"avtale_eier":"Sosiologisk institutt","utvprogramkode":"ERASMUS+","avtaleid":"151-1","eksternt_sted":"University of York","landnavn_norsk":"Storbritannia og Nord-Irland","landnavn_engelsk":"United Kingdom","fagnavn_norsk":"Sosiologi","studietypenr":7829}
,{"avtale_eier":"Institutt for sammenliknende politikk","utvprogramkode":"ERASMUS+","avtaleid":"151-2","eksternt_sted":"University of York","landnavn_norsk":"Storbritannia og Nord-Irland","landnavn_engelsk":"United Kingdom","fagnavn_norsk":"Statsvitenskap","studietypenr":7113}
,{"avtale_eier":"Institutt for informasjons- og medievitenskap","utvprogramkode":"ERASMUS+","avtaleid":"152-6","eksternt_sted":"Universiteit Gent","landnavn_norsk":"Belgia","landnavn_engelsk":"Belgium","fagnavn_norsk":"Kommunikasjon og informasjonsvitenskap","studietypenr":7461}
,{"avtale_eier":"Institutt for sammenliknende politikk","utvprogramkode":"ERASMUS+","avtaleid":"153-4","eksternt_sted":"Universität Salzburg","landnavn_norsk":"Østerrike","landnavn_engelsk":"Austria","fagnavn_norsk":"Statsvitenskap","studietypenr":8289}
,{"avtale_eier":"Institutt for økonomi","utvprogramkode":"ERASMUS+","avtaleid":"155-5","eksternt_sted":"Humboldt-Universität zu Berlin","landnavn_norsk":"Tyskland","landnavn_engelsk":"Germany","fagnavn_norsk":"Økonomi","studietypenr":7864}
,{"avtale_eier":"Institutt for geografi","utvprogramkode":"ERASMUS+","avtaleid":"158-5","eksternt_sted":"Rheinische Friedrich-Wilhelms-Universität Bonn","landnavn_norsk":"Tyskland","landnavn_engelsk":"Germany","fagnavn_norsk":"Geografi","studietypenr":7677}
,{"avtale_eier":"Institutt for geografi","utvprogramkode":"ERASMUS+","avtaleid":"161-1","eksternt_sted":"Freie Universität Berlin","landnavn_norsk":"Tyskland","landnavn_engelsk":"Germany","fagnavn_norsk":"Geografi","studietypenr":7954}
,{"avtale_eier":"Institutt for økonomi","utvprogramkode":"ERASMUS+","avtaleid":"161-12","eksternt_sted":"Freie Universität Berlin","landnavn_norsk":"Tyskland","landnavn_engelsk":"Germany","fagnavn_norsk":"Økonomi","studietypenr":7188}
,{"avtale_eier":"Institutt for geografi","utvprogramkode":"ERASMUS+","avtaleid":"163-2","eksternt_sted":"Leopold-Franzens Universität Innsbruck (Universität Innsbruck)","landnavn_norsk":"Østerrike","landnavn_engelsk":"Austria","fagnavn_norsk":"Geografi","studietypenr":7471}
,{"avtale_eier":"Universitetet i Bergen","utvprogramkode":"ERASMUS+","avtaleid":"164-5","eksternt_sted":"Karl-Franzens-Universität Graz","landnavn_norsk":"Østerrike","landnavn_engelsk":"Austria","fagnavn_norsk":"Alle fag","studietypenr":7293}
,{"avtale_eier":"Institutt for sammenliknende politikk","utvprogramkode":"ERASMUS+","avtaleid":"165-7","eksternt_sted":"Universität Wien","landnavn_norsk":"Østerrike","landnavn_engelsk":"Austria","fagnavn_norsk":"Statsvitenskap","studietypenr":7473}
,{"avtale_eier":"Institutt for sammenliknende politikk","utvprogramkode":"ERASMUS+","avtaleid":"166-5","eksternt_sted":"Universiteit Antwerpen","landnavn_norsk":"Belgia","landnavn_engelsk":"Belgium","fagnavn_norsk":"Statsvitenskap","studietypenr":7475}
,{"avtale_eier":"Institutt for sammenliknende politikk","utvprogramkode":"ERASMUS+","avtaleid":"169-3","eksternt_sted":"KU Leuven","landnavn_norsk":"Belgia","landnavn_engelsk":"Belgium","fagnavn_norsk":"Statsvitenskap"}
,{"avtale_eier":"Institutt for sammenliknende politikk","utvprogramkode":"ERASMUS+","avtaleid":"170-3","eksternt_sted":"Université de Liège","landnavn_norsk":"Belgia","landnavn_engelsk":"Belgium","fagnavn_norsk":"Statsvitenskap"}
,{"avtale_eier":"Institutt for sammenliknende politikk","utvprogramkode":"BILATERAL","avtaleid":"173-4","eksternt_sted":"Universität Bern","landnavn_norsk":"Sveits","landnavn_engelsk":"Switzerland","fagnavn_norsk":"Statsvitenskap","studietypenr":7485}
,{"avtale_eier":"Det samfunnsvitenskapelige fakultet","utvprogramkode":"ERASMUS+","avtaleid":"176-2","eksternt_sted":"Otto-Friedrich-Universität Bamberg","landnavn_norsk":"Tyskland","landnavn_engelsk":"Germany","fagnavn_norsk":"Samfunnsfag"}
,{"avtale_eier":"Institutt for sammenliknende politikk","utvprogramkode":"ERASMUS+","avtaleid":"181-4","eksternt_sted":"Vrije Universiteit Brussel","landnavn_norsk":"Belgia","landnavn_engelsk":"Belgium","fagnavn_norsk":"Statsvitenskap","studietypenr":8292}
,{"avtale_eier":"Institutt for sammenliknende politikk","utvprogramkode":"ERASMUS+","avtaleid":"182-3","eksternt_sted":"Universität Bremen","landnavn_norsk":"Tyskland","landnavn_engelsk":"Germany","fagnavn_norsk":"Statsvitenskap"}
,{"avtale_eier":"Det samfunnsvitenskapelige fakultet","utvprogramkode":"ERASMUS+","avtaleid":"182-8","eksternt_sted":"Universität Bremen","landnavn_norsk":"Tyskland","landnavn_engelsk":"Germany","fagnavn_norsk":"Europastudier"}
,{"avtale_eier":"Institutt for geografi","utvprogramkode":"ERASMUS+","avtaleid":"184-1","eksternt_sted":"Technische Universität Dortmund","landnavn_norsk":"Tyskland","landnavn_engelsk":"Germany","fagnavn_norsk":"Geografi"}
,{"avtale_eier":"Institutt for administrasjon og organisasjonsvitenskap","utvprogramkode":"ERASMUS+","avtaleid":"185-2","eksternt_sted":"Universität Kassel","landnavn_norsk":"Tyskland","landnavn_engelsk":"Germany","fagnavn_norsk":"Administrasjon og organisasjonsvitenskap"}
,{"avtale_eier":"Universitetet i Bergen","utvprogramkode":"ERASMUS+","avtaleid":"187-1","eksternt_sted":"Universität Leipzig","landnavn_norsk":"Tyskland","landnavn_engelsk":"Germany","fagnavn_norsk":"Alle fag","studietypenr":8321}
,{"avtale_eier":"Institutt for økonomi","utvprogramkode":"ERASMUS+","avtaleid":"189-4","eksternt_sted":"Johann Wolfgang Goethe-Universität Frankfurt am Main","landnavn_norsk":"Tyskland","landnavn_engelsk":"Germany","fagnavn_norsk":"Økonomi","studietypenr":7134}
,{"avtale_eier":"Institutt for geografi","utvprogramkode":"ERASMUS+","avtaleid":"193-3","eksternt_sted":"Julius-Maximilian-Universität Würzburg","landnavn_norsk":"Tyskland","landnavn_engelsk":"Germany","fagnavn_norsk":"Geografi","studietypenr":7660}
,{"avtale_eier":"Sosiologisk institutt","utvprogramkode":"ERASMUS+","avtaleid":"197-2","eksternt_sted":"Universidad de Granada","landnavn_norsk":"Spania","landnavn_engelsk":"Spain","fagnavn_norsk":"Sosiologi","studietypenr":7136}
,{"avtale_eier":"Institutt for informasjons- og medievitenskap","utvprogramkode":"ERASMUS+","avtaleid":"197-5","eksternt_sted":"Universidad de Granada","landnavn_norsk":"Spania","landnavn_engelsk":"Spain","fagnavn_norsk":"Informatikk","studietypenr":7257}
,{"avtale_eier":"Institutt for geografi","utvprogramkode":"ERASMUS+","avtaleid":"202-7","eksternt_sted":"Universidad de Salamanca","landnavn_norsk":"Spania","landnavn_engelsk":"Spain","fagnavn_norsk":"Geografi"}
,{"avtale_eier":"Institutt for geografi","utvprogramkode":"ERASMUS+","avtaleid":"203-2","eksternt_sted":"Universidad de Santiago de Compostela","landnavn_norsk":"Spania","landnavn_engelsk":"Spain","fagnavn_norsk":"Geografi","studietypenr":7512}
,{"avtale_eier":"Institutt for økonomi","utvprogramkode":"ERASMUS+","avtaleid":"205-6","eksternt_sted":"Universitat de València","landnavn_norsk":"Spania","landnavn_engelsk":"Spain","fagnavn_norsk":"Økonomi","studietypenr":7203}
,{"avtale_eier":"Institutt for geografi","utvprogramkode":"ERASMUS+","avtaleid":"208-2","eksternt_sted":"Université de Picardie Jules Verne","landnavn_norsk":"Frankrike","landnavn_engelsk":"France","fagnavn_norsk":"Geografi"}
,{"avtale_eier":"Institutt for økonomi","utvprogramkode":"ERASMUS+","avtaleid":"211-6","eksternt_sted":"Université de Caen Normandie","landnavn_norsk":"Frankrike","landnavn_engelsk":"France","fagnavn_norsk":"Samfunnsøkonomi","studietypenr":7149}
,{"avtale_eier":"Institutt for økonomi","utvprogramkode":"ERASMUS+","avtaleid":"214-3","eksternt_sted":"Université Lille Nord de France","landnavn_norsk":"Frankrike","landnavn_engelsk":"France","fagnavn_norsk":"Økonomi","studietypenr":7518}
,{"avtale_eier":"Institutt for geografi","utvprogramkode":"ERASMUS+","avtaleid":"217-4","eksternt_sted":"Université Lumière - Lyon 2","landnavn_norsk":"Frankrike","landnavn_engelsk":"France","fagnavn_norsk":"Geografi","studietypenr":7443}
,{"avtale_eier":"Institutt for økonomi","utvprogramkode":"ERASMUS+","avtaleid":"226-3","eksternt_sted":"Université Paris Nanterre","landnavn_norsk":"Frankrike","landnavn_engelsk":"France","fagnavn_norsk":"Samfunnsøkonomi","studietypenr":7525}
,{"avtale_eier":"Institutt for informasjons- og medievitenskap","utvprogramkode":"ERASMUS+","avtaleid":"226-4","eksternt_sted":"Université Paris Nanterre","landnavn_norsk":"Frankrike","landnavn_engelsk":"France","fagnavn_norsk":"Kommunikasjon og informasjonsvitenskap","studietypenr":7526}
,{"avtale_eier":"Det samfunnsvitenskapelige fakultet","utvprogramkode":"ERASMUS+","avtaleid":"229-2","eksternt_sted":"Institut d'Etudes politiques de Paris-'Sciences Po'","landnavn_norsk":"Frankrike","landnavn_engelsk":"France","fagnavn_norsk":"Samfunnsfag","studietypenr":7876}
,{"avtale_eier":"Institutt for informasjons- og medievitenskap","utvprogramkode":"ERASMUS+","avtaleid":"230-2","eksternt_sted":"Université Rennes II","landnavn_norsk":"Frankrike","landnavn_engelsk":"France","fagnavn_norsk":"Kommunikasjon og informasjonsvitenskap","studietypenr":7877}
,{"avtale_eier":"Institutt for informasjons- og medievitenskap","utvprogramkode":"ERASMUS+","avtaleid":"242-11","eksternt_sted":"Università di Bologna","landnavn_norsk":"Italia","landnavn_engelsk":"Italy","fagnavn_norsk":"Informatikk","studietypenr":7253}
,{"avtale_eier":"Institutt for sammenliknende politikk","utvprogramkode":"ERASMUS+","avtaleid":"242-8","eksternt_sted":"Università di Bologna","landnavn_norsk":"Italia","landnavn_engelsk":"Italy","fagnavn_norsk":"Statsvitenskap","studietypenr":7157}
,{"avtale_eier":"Universitetet i Bergen","utvprogramkode":"BILATERAL","avtaleid":"253-1","eksternt_sted":"McGill University","landnavn_norsk":"Canada","landnavn_engelsk":"Canada","fagnavn_norsk":"Alle fag","studietypenr":7162}
,{"avtale_eier":"Universitetet i Bergen","utvprogramkode":"BILATERAL","avtaleid":"254-1","eksternt_sted":"University of Hawaii at Hilo","landnavn_norsk":"USA","landnavn_engelsk":"USA","fagnavn_norsk":"Alle fag","studietypenr":7163}
,{"avtale_eier":"Universitetet i Bergen","utvprogramkode":"BILATERAL","avtaleid":"255-2","eksternt_sted":"North Park University","landnavn_norsk":"USA","landnavn_engelsk":"USA","fagnavn_norsk":"Alle fag","studietypenr":7164}
,{"avtale_eier":"Universitetet i Bergen","utvprogramkode":"BILATERAL","avtaleid":"258-1","eksternt_sted":"The University of Queensland","landnavn_norsk":"Australia","landnavn_engelsk":"Australia","fagnavn_norsk":"Alle fag","studietypenr":7697}
,{"avtale_eier":"Universitetet i Bergen","utvprogramkode":"BILATERAL","avtaleid":"259-1","eksternt_sted":"Monash University","landnavn_norsk":"Australia","landnavn_engelsk":"Australia","fagnavn_norsk":"Alle fag","studietypenr":7696}
,{"avtale_eier":"Universitetet i Bergen","utvprogramkode":"BILATERAL","avtaleid":"270-1","eksternt_sted":"Akita International University","landnavn_norsk":"Japan","landnavn_engelsk":"Japan","fagnavn_norsk":"Alle fag","studietypenr":7702}
,{"avtale_eier":"Universitetet i Bergen","utvprogramkode":"BILATERAL","avtaleid":"271-1","eksternt_sted":"Ritsumeikan Asia Pacific University","landnavn_norsk":"Japan","landnavn_engelsk":"Japan","fagnavn_norsk":"Alle fag","studietypenr":7167}
,{"avtale_eier":"Universitetet i Bergen","utvprogramkode":"BILATERAL","avtaleid":"274-1","eksternt_sted":"The American University Washington D.C.","landnavn_norsk":"USA","landnavn_engelsk":"USA","fagnavn_norsk":"Alle fag","studietypenr":7168}
,{"avtale_eier":"Universitetet i Bergen","utvprogramkode":"BILATERAL","avtaleid":"276-2","eksternt_sted":"The American University in Cairo","landnavn_norsk":"Egypt","landnavn_engelsk":"Egypt","fagnavn_norsk":"Alle fag","studietypenr":7881}
,{"avtale_eier":"Universitetet i Bergen","utvprogramkode":"BILATERAL","avtaleid":"279-1","eksternt_sted":"The University of Western Australia","landnavn_norsk":"Australia","landnavn_engelsk":"Australia","fagnavn_norsk":"Alle fag","studietypenr":7169}
,{"avtale_eier":"Universitetet i Bergen","utvprogramkode":"BILATERAL","avtaleid":"280-1","eksternt_sted":"University of Stellenbosch","landnavn_norsk":"Sør-Afrika","landnavn_engelsk":"South Africa","fagnavn_norsk":"Alle fag","studietypenr":7170}
,{"avtale_eier":"Institutt for sammenliknende politikk","utvprogramkode":"ERASMUS+","avtaleid":"283-1","eksternt_sted":"Institut d'Etudes Politiques de Bordeaux","landnavn_norsk":"Frankrike","landnavn_engelsk":"France","fagnavn_norsk":"Statsvitenskap","studietypenr":8294}
,{"avtale_eier":"Det samfunnsvitenskapelige fakultet","utvprogramkode":"ERASMUS+","avtaleid":"283-3","eksternt_sted":"Institut d'Etudes Politiques de Bordeaux","landnavn_norsk":"Frankrike","landnavn_engelsk":"France","fagnavn_norsk":"Samfunnsfag","studietypenr":7888}
,{"avtale_eier":"Det samfunnsvitenskapelige fakultet","utvprogramkode":"ERASMUS+","avtaleid":"285-1","eksternt_sted":"Institut d'études politiques de Grenoble","landnavn_norsk":"Frankrike","landnavn_engelsk":"France","fagnavn_norsk":"Samfunnsfag","studietypenr":7563}
,{"avtale_eier":"Institutt for geografi","utvprogramkode":"ERASMUS+","avtaleid":"288-1","eksternt_sted":"Université de Nantes","landnavn_norsk":"Frankrike","landnavn_engelsk":"France","fagnavn_norsk":"Geografi","studietypenr":7884}
,{"avtale_eier":"Institutt for sammenliknende politikk","utvprogramkode":"ERASMUS+","avtaleid":"298-6","eksternt_sted":"Université de Strasbourg","landnavn_norsk":"Frankrike","landnavn_engelsk":"France","fagnavn_norsk":"Statsvitenskap","studietypenr":7890}
,{"avtale_eier":"Institutt for sammenliknende politikk","utvprogramkode":"ERASMUS+","avtaleid":"302-1","eksternt_sted":"Vilniaus Universitetas","landnavn_norsk":"Litauen","landnavn_engelsk":"Lithuania","fagnavn_norsk":"Statsvitenskap","studietypenr":7570}
,{"avtale_eier":"Institutt for geografi","utvprogramkode":"ERASMUS+","avtaleid":"306-3","eksternt_sted":"Università degli Studi di Palermo","landnavn_norsk":"Italia","landnavn_engelsk":"Italy","fagnavn_norsk":"Økonomi og administrasjon","studietypenr":7679}
,{"avtale_eier":"Institutt for sammenliknende politikk","utvprogramkode":"ERASMUS+","avtaleid":"316-1","eksternt_sted":"Università degli Studi di Roma Tre","landnavn_norsk":"Italia","landnavn_engelsk":"Italy","fagnavn_norsk":"Statsvitenskap","studietypenr":7581}
,{"avtale_eier":"Institutt for informasjons- og medievitenskap","utvprogramkode":"ERASMUS+","avtaleid":"316-7","eksternt_sted":"Università degli Studi di Roma Tre","landnavn_norsk":"Italia","landnavn_engelsk":"Italy","fagnavn_norsk":"Journalistikk","studietypenr":7428}
,{"avtale_eier":"Institutt for geografi","utvprogramkode":"ERASMUS+","avtaleid":"324-3","eksternt_sted":"Philipps-Universität Marburg","landnavn_norsk":"Tyskland","landnavn_engelsk":"Germany","fagnavn_norsk":"Geografi","studietypenr":7595}
,{"avtale_eier":"Universitetet i Bergen","utvprogramkode":"BILATERAL","avtaleid":"343-1","eksternt_sted":"University of California, Berkeley","landnavn_norsk":"USA","landnavn_engelsk":"USA","fagnavn_norsk":"Sosiologi","studietypenr":7051}
,{"avtale_eier":"Institutt for økonomi","utvprogramkode":"BILATERAL","avtaleid":"343-6","eksternt_sted":"University of California, Berkeley","landnavn_norsk":"USA","landnavn_engelsk":"USA","fagnavn_norsk":"Økonomi","studietypenr":8207}
,{"avtale_eier":"Institutt for sammenliknende politikk","utvprogramkode":"ERASMUS+","avtaleid":"346-12","eksternt_sted":"University of Southampton","landnavn_norsk":"Storbritannia og Nord-Irland","landnavn_engelsk":"United Kingdom","fagnavn_norsk":"Statsvitenskap","studietypenr":7891}
,{"avtale_eier":"Institutt for økonomi","utvprogramkode":"ERASMUS+","avtaleid":"346-3","eksternt_sted":"University of Southampton","landnavn_norsk":"Storbritannia og Nord-Irland","landnavn_engelsk":"United Kingdom","fagnavn_norsk":"Økonomi","studietypenr":7845}
,{"avtale_eier":"Det samfunnsvitenskapelige fakultet","utvprogramkode":"ERASMUS+","avtaleid":"347-2","eksternt_sted":"Masarykova univerzita ","landnavn_norsk":"Tsjekkia","landnavn_engelsk":"Czech Republic","fagnavn_norsk":"Samfunnsfag","studietypenr":7823}
,{"avtale_eier":"Institutt for sammenliknende politikk","utvprogramkode":"ERASMUS+","avtaleid":"347-3","eksternt_sted":"Masarykova univerzita ","landnavn_norsk":"Tsjekkia","landnavn_engelsk":"Czech Republic","fagnavn_norsk":"Statsvitenskap","studietypenr":8288}
,{"avtale_eier":"Institutt for økonomi","utvprogramkode":"ERASMUS+","avtaleid":"348-2","eksternt_sted":"Universidad de Alicante","landnavn_norsk":"Spania","landnavn_engelsk":"Spain","fagnavn_norsk":"Økonomi","studietypenr":7430}
,{"avtale_eier":"Institutt for informasjons- og medievitenskap","utvprogramkode":"ERASMUS+","avtaleid":"353-2","eksternt_sted":"Universidad de Castilla-La Mancha","landnavn_norsk":"Spania","landnavn_engelsk":"Spain","fagnavn_norsk":"Informasjonsvitenskap","studietypenr":7403}
,{"avtale_eier":"Det samfunnsvitenskapelige fakultet","utvprogramkode":"ERASMUS+","avtaleid":"364-5","eksternt_sted":"Univerza v Ljubljani","landnavn_norsk":"Slovenia","landnavn_engelsk":"Slovenia","fagnavn_norsk":"Sosiologi","studietypenr":7941}
,{"avtale_eier":"Institutt for sammenliknende politikk","utvprogramkode":"ERASMUS+","avtaleid":"364-6","eksternt_sted":"Univerza v Ljubljani","landnavn_norsk":"Slovenia","landnavn_engelsk":"Slovenia","fagnavn_norsk":"Statsvitenskap","studietypenr":8041}
,{"avtale_eier":"Sosiologisk institutt","utvprogramkode":"ERASMUS+","avtaleid":"374-1","eksternt_sted":"Uniwersytet Jagiellonski w Krakowie","landnavn_norsk":"Polen","landnavn_engelsk":"Poland","fagnavn_norsk":"Sosiologi"}
,{"avtale_eier":"Institutt for sammenliknende politikk","utvprogramkode":"ERASMUS+","avtaleid":"378-1","eksternt_sted":"Albert-Ludwigs-Universität Freiburg","landnavn_norsk":"Tyskland","landnavn_engelsk":"Germany","fagnavn_norsk":"Sammenliknende politikk","studietypenr":7974}
,{"avtale_eier":"Institutt for økonomi","utvprogramkode":"ERASMUS+","avtaleid":"378-4","eksternt_sted":"Albert-Ludwigs-Universität Freiburg","landnavn_norsk":"Tyskland","landnavn_engelsk":"Germany","fagnavn_norsk":"Samfunnsøkonomi","studietypenr":7698}
,{"avtale_eier":"Institutt for geografi","utvprogramkode":"ERASMUS+","avtaleid":"382-5","eksternt_sted":"Universität Hamburg","landnavn_norsk":"Tyskland","landnavn_engelsk":"Germany","fagnavn_norsk":"Geografi","studietypenr":7301}
,{"avtale_eier":"Institutt for geografi","utvprogramkode":"ERASMUS+","avtaleid":"383-5","eksternt_sted":"Ruprecht-Karls-Universität Heidelberg","landnavn_norsk":"Tyskland","landnavn_engelsk":"Germany","fagnavn_norsk":"Geografi","studietypenr":7019}
,{"avtale_eier":"Institutt for økonomi","utvprogramkode":"ERASMUS+","avtaleid":"383-9","eksternt_sted":"Ruprecht-Karls-Universität Heidelberg","landnavn_norsk":"Tyskland","landnavn_engelsk":"Germany","fagnavn_norsk":"Økonomi","studietypenr":7617}
,{"avtale_eier":"Institutt for økonomi","utvprogramkode":"ERASMUS+","avtaleid":"384-3","eksternt_sted":"Ludwig-Maximilians-Universität München","landnavn_norsk":"Tyskland","landnavn_engelsk":"Germany","fagnavn_norsk":"Økonomi","studietypenr":7837}
,{"avtale_eier":"Institutt for sammenliknende politikk","utvprogramkode":"ERASMUS+","avtaleid":"384-4","eksternt_sted":"Ludwig-Maximilians-Universität München","landnavn_norsk":"Tyskland","landnavn_engelsk":"Germany","fagnavn_norsk":"Statsvitenskap","studietypenr":7360}
,{"avtale_eier":"Institutt for sammenliknende politikk","utvprogramkode":"ERASMUS+","avtaleid":"387-10","eksternt_sted":"Universität Potsdam","landnavn_norsk":"Tyskland","landnavn_engelsk":"Germany","fagnavn_norsk":"Statsvitenskap","studietypenr":7602}
,{"avtale_eier":"Institutt for informasjons- og medievitenskap","utvprogramkode":"ERASMUS+","avtaleid":"387-7","eksternt_sted":"Universität Potsdam","landnavn_norsk":"Tyskland","landnavn_engelsk":"Germany","fagnavn_norsk":"Kommunikasjon og informasjonsvitenskap","studietypenr":7599}
,{"avtale_eier":"Institutt for sammenliknende politikk","utvprogramkode":"ERASMUS+","avtaleid":"389-2","eksternt_sted":"Universität Rostock","landnavn_norsk":"Tyskland","landnavn_engelsk":"Germany","fagnavn_norsk":"Statsvitenskap"}
,{"avtale_eier":"Institutt for sammenliknende politikk","utvprogramkode":"ERASMUS+","avtaleid":"392-12","eksternt_sted":"Aarhus Universitet","landnavn_norsk":"Danmark","landnavn_engelsk":"Denmark","fagnavn_norsk":"Sammenliknende politikk","studietypenr":8030}
,{"avtale_eier":"Institutt for informasjons- og medievitenskap","utvprogramkode":"ERASMUS+","avtaleid":"393-5","eksternt_sted":"Københavns Universitet","landnavn_norsk":"Danmark","landnavn_engelsk":"Denmark","fagnavn_norsk":"Kommunikasjon og informasjonsvitenskap","studietypenr":7840}
,{"avtale_eier":"Institutt for økonomi","utvprogramkode":"ERASMUS+","avtaleid":"394-10","eksternt_sted":"Syddansk Universitet","landnavn_norsk":"Danmark","landnavn_engelsk":"Denmark","fagnavn_norsk":"Økonomi"}
,{"avtale_eier":"Det samfunnsvitenskapelige fakultet","utvprogramkode":"ERASMUS+","avtaleid":"395-3","eksternt_sted":"Roskilde Universitet","landnavn_norsk":"Danmark","landnavn_engelsk":"Denmark","fagnavn_norsk":"Samfunnsfag","studietypenr":7370}
,{"avtale_eier":"Institutt for informasjons- og medievitenskap","utvprogramkode":"ERASMUS+","avtaleid":"397-4","eksternt_sted":"Universitat Autònoma de Barcelona","landnavn_norsk":"Spania","landnavn_engelsk":"Spain","fagnavn_norsk":"Journalistikk","studietypenr":7030}
,{"avtale_eier":"Universitetet i Bergen","utvprogramkode":"BILATERAL","avtaleid":"406-1","eksternt_sted":"Université de Montréal","landnavn_norsk":"Canada","landnavn_engelsk":"Canada","fagnavn_norsk":"Alle fag","studietypenr":7700}
,{"avtale_eier":"Universitetet i Bergen","utvprogramkode":"BILATERAL","avtaleid":"407-2","eksternt_sted":"Boston College","landnavn_norsk":"USA","landnavn_engelsk":"USA","fagnavn_norsk":"Alle fag","studietypenr":7091}
,{"avtale_eier":"Universitetet i Bergen","utvprogramkode":"BILATERAL","avtaleid":"408-4","eksternt_sted":"University of Minnesota","landnavn_norsk":"USA","landnavn_engelsk":"USA","fagnavn_norsk":"Alle fag","studietypenr":7210}
,{"avtale_eier":"Universitetet i Bergen","utvprogramkode":"BILATERAL","avtaleid":"414-3","eksternt_sted":"Universidade Federal de Santa Catarina","landnavn_norsk":"Brasil","landnavn_engelsk":"Brazil","fagnavn_norsk":"Alle fag","studietypenr":7093}
,{"avtale_eier":"Universitetet i Bergen","utvprogramkode":"BILATERAL","avtaleid":"415-1","eksternt_sted":"State University of New York at Albany","landnavn_norsk":"USA","landnavn_engelsk":"USA","fagnavn_norsk":"Alle fag","studietypenr":7094}
,{"avtale_eier":"Universitetet i Bergen","utvprogramkode":"BILATERAL","avtaleid":"421-1","eksternt_sted":"Makerere University","landnavn_norsk":"Uganda","landnavn_engelsk":"Uganda","fagnavn_norsk":"Alle fag","studietypenr":7701}
,{"avtale_eier":"Universitetet i Bergen","utvprogramkode":"BILATERAL","avtaleid":"422-1","eksternt_sted":"The Chinese University of Hong Kong","landnavn_norsk":"Hong Kong","landnavn_engelsk":"Hong Kong","fagnavn_norsk":"Alle fag","studietypenr":7097}
,{"avtale_eier":"Universitetet i Bergen","utvprogramkode":"BILATERAL","avtaleid":"425-3","eksternt_sted":"Fudan University Shanghai","landnavn_norsk":"Kina","landnavn_engelsk":"China","fagnavn_norsk":"Alle fag","studietypenr":7100}
,{"avtale_eier":"Universitetet i Bergen","utvprogramkode":"BILATERAL","avtaleid":"428-1","eksternt_sted":"Thammasat University","landnavn_norsk":"Thailand","landnavn_engelsk":"Thailand","fagnavn_norsk":"Alle fag"}
,{"avtale_eier":"Universitetet i Bergen","utvprogramkode":"BILATERAL","avtaleid":"440-1","eksternt_sted":"Universidad de Costa Rica","landnavn_norsk":"Costa Rica","landnavn_engelsk":"Costa Rica","fagnavn_norsk":"Alle fag","studietypenr":7220}
,{"avtale_eier":"Universitetet i Bergen","utvprogramkode":"BILATERAL","avtaleid":"441-1","eksternt_sted":"Hong Kong Baptist University","landnavn_norsk":"Hong Kong","landnavn_engelsk":"Hong Kong","fagnavn_norsk":"Alle fag","studietypenr":7061}
,{"avtale_eier":"Universitetet i Bergen","utvprogramkode":"BILATERAL","avtaleid":"442-1","eksternt_sted":"Hong Kong University of Science and Technology","landnavn_norsk":"Hong Kong","landnavn_engelsk":"Hong Kong","fagnavn_norsk":"Naturfag","studietypenr":7062}
,{"avtale_eier":"Institutt for administrasjon og organisasjonsvitenskap","utvprogramkode":"BILATERAL","avtaleid":"458-1","eksternt_sted":"Centro de Investigación y Docencia Económicas, A.C.","landnavn_norsk":"Mexico","landnavn_engelsk":"Mexico","fagnavn_norsk":"Samfunnsfag","studietypenr":7063}
,{"avtale_eier":"Universitetet i Bergen","utvprogramkode":"BILATERAL","avtaleid":"478-1","eksternt_sted":"University of New Brunswick","landnavn_norsk":"Canada","landnavn_engelsk":"Canada","fagnavn_norsk":"Alle fag"}
,{"avtale_eier":"Universitetet i Bergen","utvprogramkode":"BILATERAL","avtaleid":"495-1","eksternt_sted":"Universidad Iberoamericana","landnavn_norsk":"Mexico","landnavn_engelsk":"Mexico","fagnavn_norsk":"Alle fag","studietypenr":7067}
,{"avtale_eier":"Universitetet i Bergen","utvprogramkode":"BILATERAL","avtaleid":"499-1","eksternt_sted":"Macquarie University","landnavn_norsk":"Australia","landnavn_engelsk":"Australia","fagnavn_norsk":"Alle fag","studietypenr":7068}
,{"avtale_eier":"Universitetet i Bergen","utvprogramkode":"BILATERAL","avtaleid":"502-1","eksternt_sted":"University of Hawai‘i at Mānoa","landnavn_norsk":"USA","landnavn_engelsk":"USA","fagnavn_norsk":"Alle fag","studietypenr":7071}
,{"avtale_eier":"Universitetet i Bergen","utvprogramkode":"BILATERAL","avtaleid":"503-1","eksternt_sted":"James Cook University","landnavn_norsk":"Australia","landnavn_engelsk":"Australia","fagnavn_norsk":"Alle fag","studietypenr":7072}
,{"avtale_eier":"Institutt for økonomi","utvprogramkode":"BILATERAL","avtaleid":"506-3","eksternt_sted":"University of Southampton","landnavn_norsk":"Storbritannia og Nord-Irland","landnavn_engelsk":"United Kingdom","fagnavn_norsk":"Økonomi","studietypenr":7255}
,{"avtale_eier":"Universitetet i Bergen","utvprogramkode":"BILATERAL","avtaleid":"514-1","eksternt_sted":"University of Melbourne","landnavn_norsk":"Australia","landnavn_engelsk":"Australia","fagnavn_norsk":"Alle fag","studietypenr":7076}
,{"avtale_eier":"Universitetet i Bergen","utvprogramkode":"BILATERAL","avtaleid":"519-1","eksternt_sted":"The University of Hong Kong","landnavn_norsk":"Hong Kong","landnavn_engelsk":"Hong Kong","fagnavn_norsk":"Alle fag","studietypenr":7077}
,{"avtale_eier":"Universitetet i Bergen","utvprogramkode":"BILATERAL","avtaleid":"523-1","eksternt_sted":"Ritsumeikan University","landnavn_norsk":"Japan","landnavn_engelsk":"Japan","fagnavn_norsk":"Alle fag","studietypenr":7080}
,{"avtale_eier":"Universitetet i Bergen","utvprogramkode":"BILATERAL","avtaleid":"527-1","eksternt_sted":"University of Ottawa","landnavn_norsk":"Canada","landnavn_engelsk":"Canada","fagnavn_norsk":"Alle fag","studietypenr":7081}
,{"avtale_eier":"Universitetet i Bergen","utvprogramkode":"BILATERAL","avtaleid":"528-1","eksternt_sted":"University of Alberta","landnavn_norsk":"Canada","landnavn_engelsk":"Canada","fagnavn_norsk":"Alle fag","studietypenr":7082}
,{"avtale_eier":"Sosiologisk institutt","utvprogramkode":"ERASMUS+","avtaleid":"533-10","eksternt_sted":"Universidad Complutense de Madrid","landnavn_norsk":"Spania","landnavn_engelsk":"Spain","fagnavn_norsk":"Sosiologi","studietypenr":7854}
,{"avtale_eier":"Institutt for administrasjon og organisasjonsvitenskap","utvprogramkode":"ERASMUS+","avtaleid":"533-8","eksternt_sted":"Universidad Complutense de Madrid","landnavn_norsk":"Spania","landnavn_engelsk":"Spain","fagnavn_norsk":"Statsvitenskap","studietypenr":7423}
,{"avtale_eier":"Institutt for sammenliknende politikk","utvprogramkode":"ERASMUS+","avtaleid":"534-2","eksternt_sted":"National University of Ireland, Maynooth","landnavn_norsk":"Irland","landnavn_engelsk":"Ireland","fagnavn_norsk":"Samfunnsfag","studietypenr":7425}
,{"avtale_eier":"Institutt for geografi","utvprogramkode":"ERASMUS+","avtaleid":"535-3","eksternt_sted":"Bangor University","landnavn_norsk":"Storbritannia og Nord-Irland","landnavn_engelsk":"United Kingdom","fagnavn_norsk":"Geografi","studietypenr":7406}
,{"avtale_eier":"Universitetet i Bergen","utvprogramkode":"BILATERAL","avtaleid":"538-1","eksternt_sted":"University of Ghana","landnavn_norsk":"Ghana","landnavn_engelsk":"Ghana","fagnavn_norsk":"Alle fag","studietypenr":7085}
,{"avtale_eier":"Institutt for økonomi","utvprogramkode":"ERASMUS+","avtaleid":"547-2","eksternt_sted":"Technische Universität Dresden","landnavn_norsk":"Tyskland","landnavn_engelsk":"Germany","fagnavn_norsk":"Økonomi","studietypenr":7192}
,{"avtale_eier":"Institutt for informasjons- og medievitenskap","utvprogramkode":"ERASMUS+","avtaleid":"571-1","eksternt_sted":"Eötvös Loránd Tudományegyetem","landnavn_norsk":"Ungarn","landnavn_engelsk":"Hungary","fagnavn_norsk":"Samfunnsfag","studietypenr":7707}
,{"avtale_eier":"Institutt for sammenliknende politikk","utvprogramkode":"ERASMUS+","avtaleid":"575-2","eksternt_sted":"University of Leeds","landnavn_norsk":"Storbritannia og Nord-Irland","landnavn_engelsk":"United Kingdom","fagnavn_norsk":"Samfunnsfag","studietypenr":7834}
,{"avtale_eier":"Universitetet i Bergen","utvprogramkode":"BILATERAL","avtaleid":"577-1","eksternt_sted":"Universidad de Buenos Aires","landnavn_norsk":"Argentina","landnavn_engelsk":"Argentina","fagnavn_norsk":"Samfunnsfag"}
,{"avtale_eier":"Universitetet i Bergen","utvprogramkode":"BILATERAL","avtaleid":"583-1","eksternt_sted":"Universidad Nacional de San Martín","landnavn_norsk":"Argentina","landnavn_engelsk":"Argentina","fagnavn_norsk":"Alle fag","studietypenr":7219}
,{"avtale_eier":"Det samfunnsvitenskapelige fakultet","utvprogramkode":"ERASMUS+","avtaleid":"596-1","eksternt_sted":"Latvijas Universitāte","landnavn_norsk":"Latvia","landnavn_engelsk":"Latvia","fagnavn_norsk":"Samfunnsfag"}
,{"avtale_eier":"Universitetet i Bergen","utvprogramkode":"BILATERAL","avtaleid":"600-1","eksternt_sted":"University of Sydney","landnavn_norsk":"Australia","landnavn_engelsk":"Australia","fagnavn_norsk":"Alle fag","studietypenr":7217}
,{"avtale_eier":"Institutt for informasjons- og medievitenskap","utvprogramkode":"ERASMUS+","avtaleid":"604-1","eksternt_sted":"Univerza v Mariboru","landnavn_norsk":"Slovenia","landnavn_engelsk":"Slovenia","fagnavn_norsk":"Kommunikasjon og informasjonsvitenskap"}
,{"avtale_eier":"Institutt for informasjons- og medievitenskap","utvprogramkode":"ERASMUS+","avtaleid":"604-2","eksternt_sted":"Univerza v Mariboru","landnavn_norsk":"Slovenia","landnavn_engelsk":"Slovenia","fagnavn_norsk":"Informatikk","studietypenr":7588}
,{"avtale_eier":"Universitetet i Bergen","utvprogramkode":"BILATERAL","avtaleid":"652-1","eksternt_sted":"Hakuoh Daigaku","landnavn_norsk":"Japan","landnavn_engelsk":"Japan","fagnavn_norsk":"Alle fag","studietypenr":7209}
,{"avtale_eier":"Institutt for geografi","utvprogramkode":"ERASMUS+","avtaleid":"684-4","eksternt_sted":"Uniwersytet im. Adama Mickiewicza w Poznaniu","landnavn_norsk":"Polen","landnavn_engelsk":"Poland","fagnavn_norsk":"Geografi"}
,{"avtale_eier":"Institutt for økonomi","utvprogramkode":"ERASMUS+","avtaleid":"686-1","eksternt_sted":"Uniwersytet Warszawski","landnavn_norsk":"Polen","landnavn_engelsk":"Poland","fagnavn_norsk":"Samfunnsøkonomi","studietypenr":7379}
,{"avtale_eier":"Institutt for sammenliknende politikk","utvprogramkode":"ERASMUS+","avtaleid":"689-13","eksternt_sted":"Univerzita Karlova v Praze","landnavn_norsk":"Tsjekkia","landnavn_engelsk":"Czech Republic","fagnavn_norsk":"Samfunnsfag","studietypenr":7654}
,{"avtale_eier":"Institutt for administrasjon og organisasjonsvitenskap","utvprogramkode":"ERASMUS+","avtaleid":"689-7","eksternt_sted":"Univerzita Karlova v Praze","landnavn_norsk":"Tsjekkia","landnavn_engelsk":"Czech Republic","fagnavn_norsk":"Administrasjon og organisasjonsvitenskap","studietypenr":8222}
,{"avtale_eier":"Institutt for geografi","utvprogramkode":"ERASMUS+","avtaleid":"691-15","eksternt_sted":"Göteborgs universitet","landnavn_norsk":"Sverige","landnavn_engelsk":"Sweden","fagnavn_norsk":"Geografi"}
,{"avtale_eier":"Institutt for økonomi","utvprogramkode":"ERASMUS+","avtaleid":"692-5","eksternt_sted":"Umeå universitet","landnavn_norsk":"Sverige","landnavn_engelsk":"Sweden","fagnavn_norsk":"Økonomi"}
,{"avtale_eier":"Universitetet i Bergen","utvprogramkode":"BILATERAL","avtaleid":"712-1","eksternt_sted":"University of Missouri-Columbia","landnavn_norsk":"USA","landnavn_engelsk":"USA","fagnavn_norsk":"Alle fag","studietypenr":7035}
,{"avtale_eier":"Institutt for sammenliknende politikk","utvprogramkode":"ERASMUS+","avtaleid":"719-4","eksternt_sted":"Universität Mannheim","landnavn_norsk":"Tyskland","landnavn_engelsk":"Germany","fagnavn_norsk":"Statsvitenskap","studietypenr":8291}
,{"avtale_eier":"Institutt for økonomi","utvprogramkode":"ERASMUS+","avtaleid":"719-7","eksternt_sted":"Universität Mannheim","landnavn_norsk":"Tyskland","landnavn_engelsk":"Germany","fagnavn_norsk":"Økonomi","studietypenr":7793}
,{"avtale_eier":"Sosiologisk institutt","utvprogramkode":"ERASMUS+","avtaleid":"719-8","eksternt_sted":"Universität Mannheim","landnavn_norsk":"Tyskland","landnavn_engelsk":"Germany","fagnavn_norsk":"Sosiologi","studietypenr":7183}
,{"avtale_eier":"Institutt for administrasjon og organisasjonsvitenskap","utvprogramkode":"BILATERAL","avtaleid":"760-1","eksternt_sted":"Universidad Autónoma Metropolitana","landnavn_norsk":"Mexico","landnavn_engelsk":"Mexico","fagnavn_norsk":"Samfunnsfag","studietypenr":7256}
,{"avtale_eier":"Universitetet i Bergen","utvprogramkode":"BILATERAL","avtaleid":"776-3","eksternt_sted":"National Research University - Higher School of Economics","landnavn_norsk":"Russland","landnavn_engelsk":"Russia","fagnavn_norsk":"Alle fag"}
,{"avtale_eier":"Universitetet i Bergen","utvprogramkode":"ERASMUS+","avtaleid":"780-2","eksternt_sted":"Université Jean Moulin - Lyon 3","landnavn_norsk":"Frankrike","landnavn_engelsk":"France","fagnavn_norsk":"Alle fag","studietypenr":8326}
,{"avtale_eier":"Institutt for geografi","utvprogramkode":"ERASMUS+","avtaleid":"809-1","eksternt_sted":"Universität Vechta","landnavn_norsk":"Tyskland","landnavn_engelsk":"Germany","fagnavn_norsk":"Geografi"}
,{"avtale_eier":"Institutt for informasjons- og medievitenskap","utvprogramkode":"ERASMUS+","avtaleid":"815-1","eksternt_sted":"Technische Universität Clausthal","landnavn_norsk":"Tyskland","landnavn_engelsk":"Germany","fagnavn_norsk":"Informatikk","studietypenr":7410}
,{"avtale_eier":"Universitetet i Bergen","utvprogramkode":"ERASMUS+","avtaleid":"841-10","eksternt_sted":"Lapin yliopisto","landnavn_norsk":"Finland","landnavn_engelsk":"Finland","fagnavn_norsk":"Alle fag","studietypenr":5280}
,{"avtale_eier":"Universitetet i Bergen","utvprogramkode":"ERASMUS+","avtaleid":"841-14","eksternt_sted":"Åbo Akademi","landnavn_norsk":"Finland","landnavn_engelsk":"Finland","fagnavn_norsk":"Alle fag","studietypenr":5283}
,{"avtale_eier":"Universitetet i Bergen","utvprogramkode":"ERASMUS+","avtaleid":"841-15","eksternt_sted":"Itä-Suomen Yliopisto","landnavn_norsk":"Finland","landnavn_engelsk":"Finland","fagnavn_norsk":"Alle fag","studietypenr":5284}
,{"avtale_eier":"Universitetet i Bergen","utvprogramkode":"NORDPLUS","avtaleid":"841-16","eksternt_sted":"Frodskaparsetur Føroya","landnavn_norsk":"Færøyene","landnavn_engelsk":"Faroe Islands","fagnavn_norsk":"Alle fag","studietypenr":5285}
,{"avtale_eier":"Universitetet i Bergen","utvprogramkode":"ERASMUS+","avtaleid":"841-21","eksternt_sted":"Karlstads universitet","landnavn_norsk":"Sverige","landnavn_engelsk":"Sweden","fagnavn_norsk":"Alle fag","studietypenr":5290}
,{"avtale_eier":"Universitetet i Bergen","utvprogramkode":"ERASMUS+","avtaleid":"841-22","eksternt_sted":"Linköpings universitet","landnavn_norsk":"Sverige","landnavn_engelsk":"Sweden","fagnavn_norsk":"Alle fag","studietypenr":5291}
,{"avtale_eier":"Universitetet i Bergen","utvprogramkode":"ERASMUS+","avtaleid":"841-23","eksternt_sted":"Luleå tekniska universitet","landnavn_norsk":"Sverige","landnavn_engelsk":"Sweden","fagnavn_norsk":"Alle fag","studietypenr":5292}
,{"avtale_eier":"Universitetet i Bergen","utvprogramkode":"ERASMUS+","avtaleid":"841-29","eksternt_sted":"Linnéuniversitetet","landnavn_norsk":"Sverige","landnavn_engelsk":"Sweden","fagnavn_norsk":"Alle fag","studietypenr":5298}
,{"avtale_eier":"Universitetet i Bergen","utvprogramkode":"ERASMUS+","avtaleid":"841-3","eksternt_sted":"Aarhus Universitet","landnavn_norsk":"Danmark","landnavn_engelsk":"Denmark","fagnavn_norsk":"Alle fag","studietypenr":5273}
,{"avtale_eier":"Universitetet i Bergen","utvprogramkode":"ERASMUS+","avtaleid":"841-30","eksternt_sted":"Tampereen yliopisto \/ Tammerfors universitet","landnavn_norsk":"Finland","landnavn_engelsk":"Finland","fagnavn_norsk":"Alle fag","studietypenr":8193}
,{"avtale_eier":"Institutt for sammenliknende politikk","utvprogramkode":"ERASMUS+","avtaleid":"843-10","eksternt_sted":"Vaasan yliopisto","landnavn_norsk":"Finland","landnavn_engelsk":"Finland","fagnavn_norsk":"Statsvitenskap","studietypenr":5311}
,{"avtale_eier":"Institutt for sammenliknende politikk","utvprogramkode":"ERASMUS+","avtaleid":"843-11","eksternt_sted":"Åbo Akademi","landnavn_norsk":"Finland","landnavn_engelsk":"Finland","fagnavn_norsk":"Statsvitenskap","studietypenr":8133}
,{"avtale_eier":"Institutt for sammenliknende politikk","utvprogramkode":"ERASMUS+","avtaleid":"843-16","eksternt_sted":"Stockholms universitet","landnavn_norsk":"Sverige","landnavn_engelsk":"Sweden","fagnavn_norsk":"Statsvitenskap","studietypenr":5316}
,{"avtale_eier":"Institutt for sammenliknende politikk","utvprogramkode":"ERASMUS+","avtaleid":"843-17","eksternt_sted":"Umeå universitet","landnavn_norsk":"Sverige","landnavn_engelsk":"Sweden","fagnavn_norsk":"Statsvitenskap","studietypenr":5317}
,{"avtale_eier":"Institutt for sammenliknende politikk","utvprogramkode":"ERASMUS+","avtaleid":"843-18","eksternt_sted":"Uppsala universitet","landnavn_norsk":"Sverige","landnavn_engelsk":"Sweden","fagnavn_norsk":"Statsvitenskap","studietypenr":5318}
,{"avtale_eier":"Institutt for sammenliknende politikk","utvprogramkode":"ERASMUS+","avtaleid":"843-7","eksternt_sted":"Lapin yliopisto","landnavn_norsk":"Finland","landnavn_engelsk":"Finland","fagnavn_norsk":"Statsvitenskap","studietypenr":5308}
,{"avtale_eier":"Institutt for sammenliknende politikk","utvprogramkode":"ERASMUS+","avtaleid":"843-8","eksternt_sted":"Tampereen yliopisto \/ Tammerfors universitet","landnavn_norsk":"Finland","landnavn_engelsk":"Finland","fagnavn_norsk":"Statsvitenskap","studietypenr":5309}
,{"avtale_eier":"Institutt for sammenliknende politikk","utvprogramkode":"ERASMUS+","avtaleid":"878-1","eksternt_sted":"Ege Üniversitesi","landnavn_norsk":"Tyrkia","landnavn_engelsk":"Turkey","fagnavn_norsk":"Samfunnsfag","studietypenr":7288}
,{"avtale_eier":"Institutt for økonomi","utvprogramkode":"ERASMUS+","avtaleid":"881-2","eksternt_sted":"Turun yliopisto","landnavn_norsk":"Finland","landnavn_engelsk":"Finland","fagnavn_norsk":"Økonomi"}
,{"avtale_eier":"Institutt for sammenliknende politikk","utvprogramkode":"ERASMUS+","avtaleid":"886-1","eksternt_sted":"Technische Universität Chemnitz","landnavn_norsk":"Tyskland","landnavn_engelsk":"Germany","fagnavn_norsk":"Statsvitenskap"}
,{"avtale_eier":"Institutt for sammenliknende politikk","utvprogramkode":"ERASMUS+","avtaleid":"889-1","eksternt_sted":"Bogaziçi Üniversitesi","landnavn_norsk":"Tyrkia","landnavn_engelsk":"Turkey","fagnavn_norsk":"Statsvitenskap","studietypenr":7322}
,{"avtale_eier":"Universitetet i Bergen","utvprogramkode":"BILATERAL","avtaleid":"903-2","eksternt_sted":"University of Victoria","landnavn_norsk":"Canada","landnavn_engelsk":"Canada","fagnavn_norsk":"Alle fag","studietypenr":8142}
,{"avtale_eier":"Universitetet i Bergen","utvprogramkode":"BILATERAL","avtaleid":"904-1","eksternt_sted":"Seoul National University","landnavn_norsk":"Sør-Korea","landnavn_engelsk":"South Korea","fagnavn_norsk":"Alle fag","studietypenr":7249}
,{"avtale_eier":"Universitetet i Bergen","utvprogramkode":"BILATERAL","avtaleid":"907-1","eksternt_sted":"Doshisha University","landnavn_norsk":"Japan","landnavn_engelsk":"Japan","fagnavn_norsk":"Alle fag","studietypenr":7827}
,{"avtale_eier":"Universitetet i Bergen","utvprogramkode":"BILATERAL","avtaleid":"908-1","eksternt_sted":"University of Hyderabad","landnavn_norsk":"India","landnavn_engelsk":"India","fagnavn_norsk":"Alle fag","studietypenr":7252}
,{"avtale_eier":"Universitetet i Bergen","utvprogramkode":"BILATERAL","avtaleid":"910-1","eksternt_sted":"University of New Mexico","landnavn_norsk":"USA","landnavn_engelsk":"USA","fagnavn_norsk":"Alle fag","studietypenr":7265}
,{"avtale_eier":"Universitetet i Bergen","utvprogramkode":"BILATERAL","avtaleid":"928","eksternt_sted":"University of North Dakota","landnavn_norsk":"USA","landnavn_engelsk":"USA","fagnavn_norsk":"Alle fag","studietypenr":7905}
,{"avtale_eier":"Universitetet i Bergen","utvprogramkode":"BILATERAL","avtaleid":"937","eksternt_sted":"University of Otago","landnavn_norsk":"New Zealand","landnavn_engelsk":"New Zealand","fagnavn_norsk":"Alle fag","studietypenr":7922}
,{"avtale_eier":"Universitetet i Bergen","utvprogramkode":"BILATERAL","avtaleid":"990","eksternt_sted":"University of the South Pacific","landnavn_norsk":"Fiji","landnavn_engelsk":"Fiji","fagnavn_norsk":"Sosialantropologi","studietypenr":7968}
,{"avtale_eier":"Institutt for informasjons- og medievitenskap","utvprogramkode":"ERASMUS+","avtaleid":"348-3","eksternt_sted":"Universidad de Alicante","landnavn_norsk":"Spania","landnavn_engelsk":"Spain","fagnavn_norsk":"Informatikk","studietypenr":7431}
,{"avtale_eier":"Institutt for administrasjon og organisasjonsvitenskap","utvprogramkode":"ERASMUS+","avtaleid":"186-3","eksternt_sted":"Universität Konstanz","landnavn_norsk":"Tyskland","landnavn_engelsk":"Germany","fagnavn_norsk":"Administrasjon og organisasjonsvitenskap","studietypenr":7133}
,{"avtale_eier":"Sosiologisk institutt","utvprogramkode":"ERASMUS+","avtaleid":"138-2","eksternt_sted":"University of Essex","landnavn_norsk":"Storbritannia og Nord-Irland","landnavn_engelsk":"United Kingdom","fagnavn_norsk":"Sosiologi","studietypenr":7858}
,{"avtale_eier":"Institutt for sammenliknende politikk","utvprogramkode":"ERASMUS+","avtaleid":"138-4","eksternt_sted":"University of Essex","landnavn_norsk":"Storbritannia og Nord-Irland","landnavn_engelsk":"United Kingdom","fagnavn_norsk":"Statsvitenskap","studietypenr":7456}
,{"avtale_eier":"Institutt for sammenliknende politikk","utvprogramkode":"ERASMUS+","avtaleid":"110-3","eksternt_sted":"Vrije Universiteit Amsterdam","landnavn_norsk":"Nederland","landnavn_engelsk":"Netherlands","fagnavn_norsk":"Samfunnsfag","studietypenr":7935}
,{"avtale_eier":"Institutt for sosialantropologi","utvprogramkode":"ERASMUS+","avtaleid":"110-5","eksternt_sted":"Vrije Universiteit Amsterdam","landnavn_norsk":"Nederland","landnavn_engelsk":"Netherlands","fagnavn_norsk":"Sosialantropologi","studietypenr":7830}
,{"avtale_eier":"Institutt for sammenliknende politikk","utvprogramkode":"ERASMUS+","avtaleid":"843-3","eksternt_sted":"Københavns Universitet","landnavn_norsk":"Danmark","landnavn_engelsk":"Denmark","fagnavn_norsk":"Statsvitenskap","studietypenr":5304}
,{"avtale_eier":"Institutt for sammenliknende politikk","utvprogramkode":"ERASMUS+","avtaleid":"843-4","eksternt_sted":"Syddansk Universitet","landnavn_norsk":"Danmark","landnavn_engelsk":"Denmark","fagnavn_norsk":"Statsvitenskap","studietypenr":5305}
,{"avtale_eier":"Institutt for informasjons- og medievitenskap","utvprogramkode":"ERASMUS+","avtaleid":"153-1","eksternt_sted":"Universität Salzburg","landnavn_norsk":"Østerrike","landnavn_engelsk":"Austria","fagnavn_norsk":"Kommunikasjon og informasjonsvitenskap"}
,{"avtale_eier":"Institutt for administrasjon og organisasjonsvitenskap","utvprogramkode":"ERASMUS+","avtaleid":"1166","eksternt_sted":"Zeppelin Universität","landnavn_norsk":"Tyskland","landnavn_engelsk":"Germany","fagnavn_norsk":"Samfunnsfag","studietypenr":8027}
,{"avtale_eier":"Institutt for geografi","utvprogramkode":"ERASMUS+","avtaleid":"159-4","eksternt_sted":"Friedrich-Alexander-Universität Erlangen-Nürnberg","landnavn_norsk":"Tyskland","landnavn_engelsk":"Germany","fagnavn_norsk":"Geografi","studietypenr":7614}
,{"avtale_eier":"Sosiologisk institutt","utvprogramkode":"ERASMUS+","avtaleid":"169-9","eksternt_sted":"KU Leuven","landnavn_norsk":"Belgia","landnavn_engelsk":"Belgium","fagnavn_norsk":"Sosiologi","studietypenr":7802}
,{"avtale_eier":"Det samfunnsvitenskapelige fakultet","utvprogramkode":"ERASMUS+","avtaleid":"226-5","eksternt_sted":"Université Paris Nanterre","landnavn_norsk":"Frankrike","landnavn_engelsk":"France","fagnavn_norsk":"Samfunnsfag","studietypenr":7875}
,{"avtale_eier":"Institutt for sammenliknende politikk","utvprogramkode":"ERASMUS+","avtaleid":"843-13","eksternt_sted":"Háskóli Íslands","landnavn_norsk":"Island","landnavn_engelsk":"Iceland","fagnavn_norsk":"Statsvitenskap","studietypenr":5313}
,{"avtale_eier":"Institutt for sammenliknende politikk","utvprogramkode":"ERASMUS+","avtaleid":"843-14","eksternt_sted":"Göteborgs universitet","landnavn_norsk":"Sverige","landnavn_engelsk":"Sweden","fagnavn_norsk":"Statsvitenskap","studietypenr":5314}
,{"avtale_eier":"Institutt for geografi","utvprogramkode":"ERASMUS+","avtaleid":"387-9","eksternt_sted":"Universität Potsdam","landnavn_norsk":"Tyskland","landnavn_engelsk":"Germany","fagnavn_norsk":"Geografi","studietypenr":7601}
,{"avtale_eier":"Institutt for sosialantropologi","utvprogramkode":"ERASMUS+","avtaleid":"347-6","eksternt_sted":"Masarykova univerzita ","landnavn_norsk":"Tsjekkia","landnavn_engelsk":"Czech Republic","fagnavn_norsk":"Sosialantropologi","studietypenr":7053}
,{"avtale_eier":"Institutt for informasjons- og medievitenskap","utvprogramkode":"ERASMUS+","avtaleid":"182-11","eksternt_sted":"Universität Bremen","landnavn_norsk":"Tyskland","landnavn_engelsk":"Germany","fagnavn_norsk":"Kommunikasjon og informasjonsvitenskap"}
,{"avtale_eier":"Sosiologisk institutt","utvprogramkode":"ERASMUS+","avtaleid":"182-2","eksternt_sted":"Universität Bremen","landnavn_norsk":"Tyskland","landnavn_engelsk":"Germany","fagnavn_norsk":"Sosiologi"}
,{"avtale_eier":"Institutt for sammenliknende politikk","utvprogramkode":"ERASMUS+","avtaleid":"219-2","eksternt_sted":"Institut d'études politiques d'Aix-en-Provence","landnavn_norsk":"Frankrike","landnavn_engelsk":"France","fagnavn_norsk":"Statsvitenskap","studietypenr":7874}
,{"avtale_eier":"Institutt for informasjons- og medievitenskap","utvprogramkode":"ERASMUS+","avtaleid":"108-4","eksternt_sted":"Ollscoil Luimnigh","landnavn_norsk":"Irland","landnavn_engelsk":"Ireland","fagnavn_norsk":"Journalistikk","studietypenr":7540}
,{"avtale_eier":"Institutt for sammenliknende politikk","utvprogramkode":"ERASMUS+","avtaleid":"286-1","eksternt_sted":"Institut d'études politiques de Lyon","landnavn_norsk":"Frankrike","landnavn_engelsk":"France","fagnavn_norsk":"Statsvitenskap","studietypenr":7564}
,{"avtale_eier":"Institutt for informasjons- og medievitenskap","utvprogramkode":"ERASMUS+","avtaleid":"205-8","eksternt_sted":"Universitat de València","landnavn_norsk":"Spania","landnavn_engelsk":"Spain","fagnavn_norsk":"Informatikk","studietypenr":7258}
,{"avtale_eier":"Institutt for sammenliknende politikk","utvprogramkode":"ERASMUS+","avtaleid":"374-2","eksternt_sted":"Uniwersytet Jagiellonski w Krakowie","landnavn_norsk":"Polen","landnavn_engelsk":"Poland","fagnavn_norsk":"Statsvitenskap","studietypenr":7347}
,{"avtale_eier":"Institutt for geografi","utvprogramkode":"ERASMUS+","avtaleid":"114-7","eksternt_sted":"Radboud Universiteit","landnavn_norsk":"Nederland","landnavn_engelsk":"Netherlands","fagnavn_norsk":"Geografi","studietypenr":7642}
,{"avtale_eier":"Institutt for sammenliknende politikk","utvprogramkode":"ERASMUS+","avtaleid":"113-5","eksternt_sted":"Universiteit Leiden","landnavn_norsk":"Nederland","landnavn_engelsk":"Netherlands","fagnavn_norsk":"Statsvitenskap","studietypenr":7903}
,{"avtale_eier":"Sosiologisk institutt","utvprogramkode":"ERASMUS+","avtaleid":"155-12","eksternt_sted":"Humboldt-Universität zu Berlin","landnavn_norsk":"Tyskland","landnavn_engelsk":"Germany","fagnavn_norsk":"Sosiologi","studietypenr":7115}
,{"avtale_eier":"Institutt for økonomi","utvprogramkode":"ERASMUS+","avtaleid":"122-4","eksternt_sted":"Universidade Nova de Lisboa","landnavn_norsk":"Portugal","landnavn_engelsk":"Portugal","fagnavn_norsk":"Økonomi"}
,{"avtale_eier":"Institutt for geografi","utvprogramkode":"ERASMUS+","avtaleid":"1223","eksternt_sted":"Université du Luxembourg","landnavn_norsk":"Luxembourg","landnavn_engelsk":"Luxembourg","fagnavn_norsk":"Geografi","studietypenr":8144}
,{"avtale_eier":"Universitetet i Bergen","utvprogramkode":"BILATERAL","avtaleid":"901-2","eksternt_sted":"USA","landnavn_norsk":"USA","landnavn_engelsk":"USA","fagnavn_norsk":"Alle fag","studietypenr":8379}
,{"avtale_eier":"Institutt for sammenliknende politikk","utvprogramkode":"ERASMUS+","avtaleid":"684-1","eksternt_sted":"Uniwersytet im. Adama Mickiewicza w Poznaniu","landnavn_norsk":"Polen","landnavn_engelsk":"Poland","fagnavn_norsk":"Samfunnsfag","studietypenr":7376}
,{"avtale_eier":"Universitetet i Bergen","utvprogramkode":"BILATERAL","avtaleid":"437-2","eksternt_sted":"University of Washington","landnavn_norsk":"USA","landnavn_engelsk":"USA","fagnavn_norsk":"Alle fag","studietypenr":7060}
,{"avtale_eier":"Universitetet i Bergen","utvprogramkode":"ERASMUS+ICM","avtaleid":"1264","eksternt_sted":"Birzeit University","landnavn_norsk":"Palestina","landnavn_engelsk":"Palestine","fagnavn_norsk":"Alle fag","studietypenr":8200}
,{"avtale_eier":"Institutt for økonomi","utvprogramkode":"ERASMUS+","avtaleid":"104-5","eksternt_sted":"Università degli Studi di Torino","landnavn_norsk":"Italia","landnavn_engelsk":"Italy","fagnavn_norsk":"Økonomi","studietypenr":7150}
,{"avtale_eier":"Institutt for administrasjon og organisasjonsvitenskap","utvprogramkode":"ERASMUS+","avtaleid":"115-2","eksternt_sted":"Erasmus Universiteit Rotterdam","landnavn_norsk":"Nederland","landnavn_engelsk":"Netherlands","fagnavn_norsk":"Samfunnsfag","studietypenr":7153}
,{"avtale_eier":"Institutt for geografi","utvprogramkode":"ERASMUS+","avtaleid":"128-6","eksternt_sted":"Stockholms universitet","landnavn_norsk":"Sverige","landnavn_engelsk":"Sweden","fagnavn_norsk":"Geografi","studietypenr":7740}
,{"avtale_eier":"Institutt for sammenliknende politikk","utvprogramkode":"ERASMUS+","avtaleid":"161-2","eksternt_sted":"Freie Universität Berlin","landnavn_norsk":"Tyskland","landnavn_engelsk":"Germany","fagnavn_norsk":"Statsvitenskap","studietypenr":7118}
,{"avtale_eier":"Universitetet i Bergen","utvprogramkode":"BILATERAL","avtaleid":"256-2","eksternt_sted":"Purdue University","landnavn_norsk":"USA","landnavn_engelsk":"USA","fagnavn_norsk":"Sammenliknende politikk","studietypenr":7165}
,{"avtale_eier":"Institutt for administrasjon og organisasjonsvitenskap","utvprogramkode":"ERASMUS+","avtaleid":"283-2","eksternt_sted":"Institut d'Etudes Politiques de Bordeaux","landnavn_norsk":"Frankrike","landnavn_engelsk":"France","fagnavn_norsk":"Administrasjon og organisasjonsvitenskap","studietypenr":7620}
,{"avtale_eier":"Institutt for økonomi","utvprogramkode":"ERASMUS+","avtaleid":"375-6","eksternt_sted":"Christian-Albrechts-Universität zu Kiel","landnavn_norsk":"Tyskland","landnavn_engelsk":"Germany","fagnavn_norsk":"Samfunnsøkonomi","studietypenr":7011}
,{"avtale_eier":"Universitetet i Bergen","utvprogramkode":"BILATERAL","avtaleid":"877-1","eksternt_sted":"Hokkaido University","landnavn_norsk":"Japan","landnavn_engelsk":"Japan","fagnavn_norsk":"Alle fag","studietypenr":7277}
,{"avtale_eier":"Institutt for geografi","utvprogramkode":"ERASMUS+","avtaleid":"345-6","eksternt_sted":"University of Reading","landnavn_norsk":"Storbritannia og Nord-Irland","landnavn_engelsk":"United Kingdom","fagnavn_norsk":"Geografi","studietypenr":7821}
,{"avtale_eier":"Universitetet i Bergen","utvprogramkode":"BILATERAL","avtaleid":"418-1","eksternt_sted":"University of Cape Town","landnavn_norsk":"Sør-Afrika","landnavn_engelsk":"South Africa","fagnavn_norsk":"Alle fag","studietypenr":7095}
,{"avtale_eier":"Institutt for geografi","utvprogramkode":"ERASMUS+","avtaleid":"386-3","eksternt_sted":"Carl von Ossietzky Universität Oldenburg","landnavn_norsk":"Tyskland","landnavn_engelsk":"Germany","fagnavn_norsk":"Økologi","studietypenr":7362}
,{"avtale_eier":"Institutt for økonomi","utvprogramkode":"ERASMUS+","avtaleid":"387-1","eksternt_sted":"Universität Potsdam","landnavn_norsk":"Tyskland","landnavn_engelsk":"Germany","fagnavn_norsk":"Økonomi","studietypenr":8024}
,{"avtale_eier":"Universitetet i Bergen","utvprogramkode":"ERASMUS+","avtaleid":"858-2","eksternt_sted":"Université Claude Bernard Lyon 1","landnavn_norsk":"Frankrike","landnavn_engelsk":"France","fagnavn_norsk":"Alle fag","studietypenr":8324}
,{"avtale_eier":"Institutt for sammenliknende politikk","utvprogramkode":"ERASMUS+","avtaleid":"687-1","eksternt_sted":"Collegium Civitas w Warszawie","landnavn_norsk":"Polen","landnavn_engelsk":"Poland","fagnavn_norsk":"Samfunnsfag"}
,{"avtale_eier":"Institutt for informasjons- og medievitenskap","utvprogramkode":"ERASMUS+","avtaleid":"688-1","eksternt_sted":"Dolnoslaska Szkola Wyzsza","landnavn_norsk":"Polen","landnavn_engelsk":"Poland","fagnavn_norsk":"Kommunikasjon og informasjonsvitenskap","studietypenr":7032}
,{"avtale_eier":"Universitetet i Bergen","utvprogramkode":"ERASMUS+","avtaleid":"841-26","eksternt_sted":"Umeå universitet","landnavn_norsk":"Sverige","landnavn_engelsk":"Sweden","fagnavn_norsk":"Alle fag","studietypenr":5295}
,{"avtale_eier":"Universitetet i Bergen","utvprogramkode":"ERASMUS+","avtaleid":"841-27","eksternt_sted":"Uppsala universitet","landnavn_norsk":"Sverige","landnavn_engelsk":"Sweden","fagnavn_norsk":"Alle fag","studietypenr":5296}
,{"avtale_eier":"Institutt for geografi","utvprogramkode":"ERASMUS+","avtaleid":"882-1","eksternt_sted":"Háskóli Íslands","landnavn_norsk":"Island","landnavn_engelsk":"Iceland","fagnavn_norsk":"Geografi","studietypenr":7292}
,{"avtale_eier":"Universitetet i Bergen","utvprogramkode":"ERASMUS+","avtaleid":"882-2","eksternt_sted":"Háskóli Íslands","landnavn_norsk":"Island","landnavn_engelsk":"Iceland","fagnavn_norsk":"Alle fag","studietypenr":7975}
,{"avtale_eier":"Universitetet i Bergen","utvprogramkode":"ERASMUS+","avtaleid":"841-11","eksternt_sted":"Oulun yliopisto","landnavn_norsk":"Finland","landnavn_engelsk":"Finland","fagnavn_norsk":"Alle fag","studietypenr":8132}
,{"avtale_eier":"Universitetet i Bergen","utvprogramkode":"ERASMUS+","avtaleid":"841-12","eksternt_sted":"Turun yliopisto","landnavn_norsk":"Finland","landnavn_engelsk":"Finland","fagnavn_norsk":"Alle fag","studietypenr":5281}
,{"avtale_eier":"Institutt for sammenliknende politikk","utvprogramkode":"ERASMUS+","avtaleid":"144-2","eksternt_sted":"Keele University","landnavn_norsk":"Storbritannia og Nord-Irland","landnavn_engelsk":"United Kingdom","fagnavn_norsk":"Samfunnsfag","studietypenr":7111}
,{"avtale_eier":"Universitetet i Bergen","utvprogramkode":"BILATERAL","avtaleid":"922-1","eksternt_sted":"Yamanashi Gakuin Daigaku","landnavn_norsk":"Japan","landnavn_engelsk":"Japan","fagnavn_norsk":"Alle fag","studietypenr":7828}
,{"avtale_eier":"Institutt for sosialantropologi","utvprogramkode":"ERASMUS+","avtaleid":"126-13","eksternt_sted":"Lunds universitet","landnavn_norsk":"Sverige","landnavn_engelsk":"Sweden","fagnavn_norsk":"Sosialantropologi"}
,{"avtale_eier":"Det samfunnsvitenskapelige fakultet","utvprogramkode":"ERASMUS+","avtaleid":"116-2","eksternt_sted":"Universiteit Utrecht","landnavn_norsk":"Nederland","landnavn_engelsk":"Netherlands","fagnavn_norsk":"Samfunnsfag","studietypenr":7548}
,{"avtale_eier":"Institutt for geografi","utvprogramkode":"ERASMUS+","avtaleid":"136-2","eksternt_sted":"Aberystwyth University","landnavn_norsk":"Storbritannia og Nord-Irland","landnavn_engelsk":"United Kingdom","fagnavn_norsk":"Geografi","studietypenr":7107}
,{"avtale_eier":"Institutt for sammenliknende politikk","utvprogramkode":"BILATERAL","avtaleid":"1203-1","eksternt_sted":"Beijing Foreign Studies University","landnavn_norsk":"Kina","landnavn_engelsk":"China","fagnavn_norsk":"Samfunnsfag","studietypenr":8332}
,{"avtale_eier":"Institutt for geografi","utvprogramkode":"ERASMUS+","avtaleid":"1009","eksternt_sted":"University of Manchester","landnavn_norsk":"Storbritannia og Nord-Irland","landnavn_engelsk":"United Kingdom","fagnavn_norsk":"Geografi","studietypenr":7984}
,{"avtale_eier":"Institutt for geografi","utvprogramkode":"ERASMUS+","avtaleid":"390-2","eksternt_sted":"Universität Trier","landnavn_norsk":"Tyskland","landnavn_engelsk":"Germany","fagnavn_norsk":"Miljøforvaltning og planlegging"}
,{"avtale_eier":"Institutt for sammenliknende politikk","utvprogramkode":"ERASMUS+","avtaleid":"397-3","eksternt_sted":"Universitat Autònoma de Barcelona","landnavn_norsk":"Spania","landnavn_engelsk":"Spain","fagnavn_norsk":"Statsvitenskap","studietypenr":7029}
,{"avtale_eier":"Institutt for geografi","utvprogramkode":"ERASMUS+","avtaleid":"955","eksternt_sted":"Coventry University","landnavn_norsk":"Storbritannia og Nord-Irland","landnavn_engelsk":"United Kingdom","fagnavn_norsk":"Geografi","studietypenr":7949}
,{"avtale_eier":"Universitetet i Bergen","utvprogramkode":"BILATERAL","avtaleid":"343-2","eksternt_sted":"University of California, Berkeley","landnavn_norsk":"USA","landnavn_engelsk":"USA","fagnavn_norsk":"Alle fag"}
,{"avtale_eier":"Institutt for sammenliknende politikk","utvprogramkode":"ERASMUS+","avtaleid":"301-4","eksternt_sted":"Vytauto Didžiojo Universitetas","landnavn_norsk":"Litauen","landnavn_engelsk":"Lithuania","fagnavn_norsk":"Samfunnsfag"}
,{"avtale_eier":"Universitetet i Bergen","utvprogramkode":"BILATERAL","avtaleid":"501-1","eksternt_sted":"Pontificia Universidad Católica del Perú","landnavn_norsk":"Peru","landnavn_engelsk":"Peru","fagnavn_norsk":"Alle fag","studietypenr":7070}
,{"avtale_eier":"Institutt for økonomi","utvprogramkode":"ERASMUS+","avtaleid":"207-2","eksternt_sted":"Universidad de Zaragoza","landnavn_norsk":"Spania","landnavn_engelsk":"Spain","fagnavn_norsk":"Samfunnsøkonomi"}
,{"avtale_eier":"Universitetet i Bergen","utvprogramkode":"ERASMUS+","avtaleid":"841-19","eksternt_sted":"Háskólinn í Reykjavík","landnavn_norsk":"Island","landnavn_engelsk":"Iceland","fagnavn_norsk":"Alle fag","studietypenr":5288}
,{"avtale_eier":"Universitetet i Bergen","utvprogramkode":"ERASMUS+","avtaleid":"841-2","eksternt_sted":"Aalborg Universitet","landnavn_norsk":"Danmark","landnavn_engelsk":"Denmark","fagnavn_norsk":"Alle fag","studietypenr":5272}
,{"avtale_eier":"Institutt for sammenliknende politikk","utvprogramkode":"BILATERAL","avtaleid":"405-1","eksternt_sted":"Moscow State Institute of International Relations (University) of Ministry of Foreign Affairs","landnavn_norsk":"Russland","landnavn_engelsk":"Russia","fagnavn_norsk":"Statsvitenskap"}
,{"avtale_eier":"Sosiologisk institutt","utvprogramkode":"ERASMUS+ICM","avtaleid":"1139","eksternt_sted":"Charles Darwin University","landnavn_norsk":"Australia","landnavn_engelsk":"Australia","fagnavn_norsk":"Samfunnsfag","studietypenr":8037}
,{"avtale_eier":"Institutt for sammenliknende politikk","utvprogramkode":"ERASMUS+","avtaleid":"114-1","eksternt_sted":"Radboud Universiteit","landnavn_norsk":"Nederland","landnavn_engelsk":"Netherlands","fagnavn_norsk":"Sammenliknende politikk","studietypenr":8297}
,{"avtale_eier":"Universitetet i Bergen","utvprogramkode":"ERASMUS+","avtaleid":"841-6","eksternt_sted":"Syddansk Universitet","landnavn_norsk":"Danmark","landnavn_engelsk":"Denmark","fagnavn_norsk":"Alle fag","studietypenr":5276}
,{"avtale_eier":"Universitetet i Bergen","utvprogramkode":"ERASMUS+","avtaleid":"841-7","eksternt_sted":"Grønlands universitet Ilisimatusarfik","landnavn_norsk":"Grønland","landnavn_engelsk":"Greenland","fagnavn_norsk":"Alle fag","studietypenr":5277}
,{"avtale_eier":"Institutt for informasjons- og medievitenskap","utvprogramkode":"ERASMUS+","avtaleid":"392-4","eksternt_sted":"Aarhus Universitet","landnavn_norsk":"Danmark","landnavn_engelsk":"Denmark","fagnavn_norsk":"Kommunikasjon og informasjonsvitenskap"}
,{"avtale_eier":"Universitetet i Bergen","utvprogramkode":"BILATERAL","avtaleid":"905-1","eksternt_sted":"Tokai Daigaku","landnavn_norsk":"Japan","landnavn_engelsk":"Japan","fagnavn_norsk":"Alle fag"}
,{"avtale_eier":"Universitetet i Bergen","utvprogramkode":"BILATERAL","avtaleid":"906-1","eksternt_sted":"Josai International University","landnavn_norsk":"Japan","landnavn_engelsk":"Japan","fagnavn_norsk":"Alle fag","studietypenr":7251}
,{"avtale_eier":"Institutt for økonomi","utvprogramkode":"ERASMUS+","avtaleid":"651-3","eksternt_sted":"Linköpings universitet","landnavn_norsk":"Sverige","landnavn_engelsk":"Sweden","fagnavn_norsk":"Økonomi"}
,{"avtale_eier":"Institutt for informasjons- og medievitenskap","utvprogramkode":"ERASMUS+","avtaleid":"190-3","eksternt_sted":"Universität Osnabrück","landnavn_norsk":"Tyskland","landnavn_engelsk":"Germany","fagnavn_norsk":"Informasjonsvitenskap","studietypenr":7938}
,{"avtale_eier":"Institutt for økonomi","utvprogramkode":"ERASMUS+","avtaleid":"810-2","eksternt_sted":"Aix-Marseille Université","landnavn_norsk":"Frankrike","landnavn_engelsk":"France","fagnavn_norsk":"Økonomi","studietypenr":7399}
,{"avtale_eier":"Institutt for økonomi","utvprogramkode":"ERASMUS+","avtaleid":"133-3","eksternt_sted":"Oulun yliopisto","landnavn_norsk":"Finland","landnavn_engelsk":"Finland","fagnavn_norsk":"Økonomi"}
,{"avtale_eier":"Institutt for økonomi","utvprogramkode":"ERASMUS+","avtaleid":"1330","eksternt_sted":"Lappeenrannan teknillinen korkeakoulu","landnavn_norsk":"Finland","landnavn_engelsk":"Finland","fagnavn_norsk":"Økonomi"}
,{"avtale_eier":"Institutt for økonomi","utvprogramkode":"ERASMUS+","avtaleid":"1331","eksternt_sted":"Vaasan yliopisto","landnavn_norsk":"Finland","landnavn_engelsk":"Finland","fagnavn_norsk":"Økonomi"}
,{"avtale_eier":"Universitetet i Bergen","utvprogramkode":"BILATERAL","avtaleid":"505-1","eksternt_sted":"Universidad de Guanajuato","landnavn_norsk":"Mexico","landnavn_engelsk":"Mexico","fagnavn_norsk":"Alle fag","studietypenr":7074}
,{"avtale_eier":"Universitetet i Bergen","utvprogramkode":"BILATERAL","avtaleid":"252-1","eksternt_sted":"University of Waterloo","landnavn_norsk":"Canada","landnavn_engelsk":"Canada","fagnavn_norsk":"Alle fag","studietypenr":7161}
,{"avtale_eier":"Universitetet i Bergen","utvprogramkode":"BILATERAL","avtaleid":"1174","eksternt_sted":"Universidade Estadual de Campinas","landnavn_norsk":"Brasil","landnavn_engelsk":"Brazil","fagnavn_norsk":"Alle fag","studietypenr":8044}
,{"avtale_eier":"Universitetet i Bergen","utvprogramkode":"BILATERAL","avtaleid":"423-1","eksternt_sted":"Waseda University","landnavn_norsk":"Japan","landnavn_engelsk":"Japan","fagnavn_norsk":"Alle fag","studietypenr":7098}
,{"avtale_eier":"Universitetet i Bergen","utvprogramkode":"ERASMUS+","avtaleid":"352-1","eksternt_sted":"University of Hull","landnavn_norsk":"Storbritannia og Nord-Irland","landnavn_engelsk":"United Kingdom","fagnavn_norsk":"Alle fag","studietypenr":7674}
,{"avtale_eier":"Universitetet i Bergen","utvprogramkode":"BILATERAL","avtaleid":"427-3","eksternt_sted":"Keimyung University","landnavn_norsk":"Sør-Korea","landnavn_engelsk":"South Korea","fagnavn_norsk":"Alle fag"}
,{"avtale_eier":"Institutt for økonomi","utvprogramkode":"ERASMUS+","avtaleid":"691-8","eksternt_sted":"Göteborgs universitet","landnavn_norsk":"Sverige","landnavn_engelsk":"Sweden","fagnavn_norsk":"Økonomi"}
,{"avtale_eier":"Institutt for geografi","utvprogramkode":"ERASMUS+","avtaleid":"397-8","eksternt_sted":"Universitat Autònoma de Barcelona","landnavn_norsk":"Spania","landnavn_engelsk":"Spain","fagnavn_norsk":"Geografi","studietypenr":7089}
,{"avtale_eier":"Universitetet i Bergen","utvprogramkode":"BILATERAL","avtaleid":"521-1","eksternt_sted":"Hokkaido Kyoiku Daigaku","landnavn_norsk":"Japan","landnavn_engelsk":"Japan","fagnavn_norsk":"Alle fag","studietypenr":7078}
,{"avtale_eier":"Universitetet i Bergen","utvprogramkode":"BILATERAL","avtaleid":"522-1","eksternt_sted":"Keio University","landnavn_norsk":"Japan","landnavn_engelsk":"Japan","fagnavn_norsk":"Alle fag","studietypenr":7079}
,{"avtale_eier":"Det samfunnsvitenskapelige fakultet","utvprogramkode":"ERASMUS+","avtaleid":"863-1","eksternt_sted":"Politechnika Bialostocka","landnavn_norsk":"Polen","landnavn_engelsk":"Poland","fagnavn_norsk":"Samfunnsfag"}
,{"avtale_eier":"Institutt for informasjons- og medievitenskap","utvprogramkode":"ERASMUS+","avtaleid":"233-2","eksternt_sted":"Université Toulouse 1 Capitole","landnavn_norsk":"Frankrike","landnavn_engelsk":"France","fagnavn_norsk":"Medier og kommunikasjon","studietypenr":7531}
,{"avtale_eier":"Universitetet i Bergen","utvprogramkode":"ERASMUS+","avtaleid":"302-5","eksternt_sted":"Vilniaus Universitetas","landnavn_norsk":"Litauen","landnavn_engelsk":"Lithuania","fagnavn_norsk":"Alle fag","studietypenr":8305}
,{"avtale_eier":"Institutt for geografi","utvprogramkode":"ERASMUS+","avtaleid":"381-9","eksternt_sted":"Universität Greifswald","landnavn_norsk":"Tyskland","landnavn_engelsk":"Germany","fagnavn_norsk":"Geografi","studietypenr":7246}
,{"avtale_eier":"Sosiologisk institutt","utvprogramkode":"ERASMUS+","avtaleid":"779-1","eksternt_sted":"ISCTE - Instituto Universitário de Lisboa","landnavn_norsk":"Portugal","landnavn_engelsk":"Portugal","fagnavn_norsk":"Sosiologi","studietypenr":7732}
,{"avtale_eier":"Institutt for sammenliknende politikk","utvprogramkode":"ERASMUS+","avtaleid":"309-1","eksternt_sted":"Universiteit Maastricht","landnavn_norsk":"Nederland","landnavn_engelsk":"Netherlands","fagnavn_norsk":"Statsvitenskap","studietypenr":8295}
,{"avtale_eier":"Institutt for informasjons- og medievitenskap","utvprogramkode":"ERASMUS+","avtaleid":"209-2","eksternt_sted":"Université Bordeaux Montaigne","landnavn_norsk":"Frankrike","landnavn_engelsk":"France","fagnavn_norsk":"Journalistikk"}
,{"avtale_eier":"Institutt for geografi","utvprogramkode":"ERASMUS+","avtaleid":"689-9","eksternt_sted":"Univerzita Karlova v Praze","landnavn_norsk":"Tsjekkia","landnavn_engelsk":"Czech Republic","fagnavn_norsk":"Geografi","studietypenr":7244}
,{"avtale_eier":"Institutt for økonomi","utvprogramkode":"ERASMUS+","avtaleid":"558-1","eksternt_sted":"CY Cergy Paris Université","landnavn_norsk":"Frankrike","landnavn_engelsk":"France","fagnavn_norsk":"Økonomi","studietypenr":7326}
,{"avtale_eier":"Det samfunnsvitenskapelige fakultet","utvprogramkode":"BILATERAL","avtaleid":"1021","eksternt_sted":"Universidad Nacional de Colombia","landnavn_norsk":"Colombia","landnavn_engelsk":"Colombia","fagnavn_norsk":"Samfunnsfag","studietypenr":8034}
,{"avtale_eier":"Institutt for sammenliknende politikk","utvprogramkode":"ERASMUS+","avtaleid":"202-1","eksternt_sted":"Universidad de Salamanca","landnavn_norsk":"Spania","landnavn_engelsk":"Spain","fagnavn_norsk":"Samfunnsfag","studietypenr":8270}
,{"avtale_eier":"Universitetet i Bergen","utvprogramkode":"ERASMUS+","avtaleid":"197-1","eksternt_sted":"Universidad de Granada","landnavn_norsk":"Spania","landnavn_engelsk":"Spain","fagnavn_norsk":"Alle fag","studietypenr":8323}
,{"avtale_eier":"Institutt for informasjons- og medievitenskap","utvprogramkode":"ERASMUS+","avtaleid":"114-3","eksternt_sted":"Radboud Universiteit","landnavn_norsk":"Nederland","landnavn_engelsk":"Netherlands","fagnavn_norsk":"Kommunikasjon og informasjonsvitenskap","studietypenr":7684}
,{"avtale_eier":"Universitetet i Bergen","utvprogramkode":"BILATERAL","avtaleid":"447-2","eksternt_sted":"Montana State University-Bozeman","landnavn_norsk":"USA","landnavn_engelsk":"USA","fagnavn_norsk":"Alle fag","studietypenr":7699}
,{"avtale_eier":"Universitetet i Bergen","utvprogramkode":"BILATERAL","avtaleid":"529-1","eksternt_sted":"Dalhousie University","landnavn_norsk":"Canada","landnavn_engelsk":"Canada","fagnavn_norsk":"Alle fag","studietypenr":7083}
,{"avtale_eier":"Universitetet i Bergen","utvprogramkode":"ERASMUS+","avtaleid":"841-13","eksternt_sted":"Vaasan yliopisto","landnavn_norsk":"Finland","landnavn_engelsk":"Finland","fagnavn_norsk":"Alle fag","studietypenr":5282}
,{"avtale_eier":"Institutt for økonomi","utvprogramkode":"ERASMUS+","avtaleid":"393-14","eksternt_sted":"Københavns Universitet","landnavn_norsk":"Danmark","landnavn_engelsk":"Denmark","fagnavn_norsk":"Økonomi","studietypenr":8215}
,{"avtale_eier":"Det samfunnsvitenskapelige fakultet","utvprogramkode":"ERASMUS+","avtaleid":"370-1","eksternt_sted":"Trnavská univerzita","landnavn_norsk":"Slovakia","landnavn_engelsk":"Slovakia","fagnavn_norsk":"Samfunnsfag"}
,{"avtale_eier":"Universitetet i Bergen","utvprogramkode":"ERASMUS+","avtaleid":"841-5","eksternt_sted":"Roskilde Universitet","landnavn_norsk":"Danmark","landnavn_engelsk":"Denmark","fagnavn_norsk":"Alle fag","studietypenr":5275}
,{"avtale_eier":"Universitetet i Bergen","utvprogramkode":"BILATERAL","avtaleid":"585-1","eksternt_sted":"Universidad de Chile","landnavn_norsk":"Chile","landnavn_engelsk":"Chile","fagnavn_norsk":"Alle fag","studietypenr":7240}
,{"avtale_eier":"Institutt for informasjons- og medievitenskap","utvprogramkode":"ERASMUS+","avtaleid":"719-2","eksternt_sted":"Universität Mannheim","landnavn_norsk":"Tyskland","landnavn_engelsk":"Germany","fagnavn_norsk":"Kommunikasjon og informasjonsvitenskap","studietypenr":7038}
,{"avtale_eier":"Institutt for informasjons- og medievitenskap","utvprogramkode":"ERASMUS+","avtaleid":"228-3","eksternt_sted":"Université Sorbonne Paris Nord","landnavn_norsk":"Frankrike","landnavn_engelsk":"France","fagnavn_norsk":"Kommunikasjon og informasjonsvitenskap","studietypenr":7529}
,{"avtale_eier":"Institutt for administrasjon og organisasjonsvitenskap","utvprogramkode":"ERASMUS+","avtaleid":"387-3","eksternt_sted":"Universität Potsdam","landnavn_norsk":"Tyskland","landnavn_engelsk":"Germany","fagnavn_norsk":"Administrasjon og organisasjonsvitenskap","studietypenr":7364}
,{"avtale_eier":"Universitetet i Bergen","utvprogramkode":"BILATERAL","avtaleid":"260-1","eksternt_sted":"The University of Waikato","landnavn_norsk":"New Zealand","landnavn_engelsk":"New Zealand","fagnavn_norsk":"Alle fag","studietypenr":7215}
,{"avtale_eier":"Universitetet i Bergen","utvprogramkode":"BILATERAL","avtaleid":"261-1","eksternt_sted":"Pontificia Universidad Católica de Chile","landnavn_norsk":"Chile","landnavn_engelsk":"Chile","fagnavn_norsk":"Alle fag"}
,{"avtale_eier":"Universitetet i Bergen","utvprogramkode":"ERASMUS+","avtaleid":"841-17","eksternt_sted":"Háskóli Íslands","landnavn_norsk":"Island","landnavn_engelsk":"Iceland","fagnavn_norsk":"Alle fag","studietypenr":5286}
,{"avtale_eier":"Universitetet i Bergen","utvprogramkode":"ERASMUS+","avtaleid":"841-18","eksternt_sted":"Háskólinn á Akureyri","landnavn_norsk":"Island","landnavn_engelsk":"Iceland","fagnavn_norsk":"Alle fag","studietypenr":5287}
,{"avtale_eier":"Institutt for sammenliknende politikk","utvprogramkode":"ERASMUS+","avtaleid":"131-2","eksternt_sted":"Helsingin yliopisto \/ Helsingfors universitet","landnavn_norsk":"Finland","landnavn_engelsk":"Finland","fagnavn_norsk":"Samfunnsfag"}
,{"avtale_eier":"Institutt for geografi","utvprogramkode":"ERASMUS+","avtaleid":"122-1","eksternt_sted":"Universidade Nova de Lisboa","landnavn_norsk":"Portugal","landnavn_engelsk":"Portugal","fagnavn_norsk":"Modellbasert samfunnsplanlegging (systemdynamikk)","studietypenr":7283}
,{"avtale_eier":"Institutt for sammenliknende politikk","utvprogramkode":"ERASMUS+","avtaleid":"696-3","eksternt_sted":"Universität Duisburg-Essen","landnavn_norsk":"Tyskland","landnavn_engelsk":"Germany","fagnavn_norsk":"Sammenliknende politikk","studietypenr":8225}
,{"avtale_eier":"Institutt for økonomi","utvprogramkode":"ERASMUS+","avtaleid":"132-6","eksternt_sted":"Jyväskylän yliopisto","landnavn_norsk":"Finland","landnavn_engelsk":"Finland","fagnavn_norsk":"Økonomi"}
,{"avtale_eier":"Universitetet i Bergen","utvprogramkode":"BILATERAL","avtaleid":"1251","eksternt_sted":"Carroll College","landnavn_norsk":"USA","landnavn_engelsk":"USA","fagnavn_norsk":"Alle fag","studietypenr":8176}
,{"avtale_eier":"Institutt for geografi","utvprogramkode":"ERASMUS+","avtaleid":"1265","eksternt_sted":"University of St. Andrews","landnavn_norsk":"Storbritannia og Nord-Irland","landnavn_engelsk":"United Kingdom","fagnavn_norsk":"Geografi","studietypenr":8201}
,{"avtale_eier":"Institutt for geografi","utvprogramkode":"ERASMUS+","avtaleid":"127-1","eksternt_sted":"Örebro universitet","landnavn_norsk":"Sverige","landnavn_engelsk":"Sweden","fagnavn_norsk":"Geografi","studietypenr":8218}
,{"avtale_eier":"Institutt for sammenliknende politikk","utvprogramkode":"ERASMUS+","avtaleid":"843-2","eksternt_sted":"Aarhus Universitet","landnavn_norsk":"Danmark","landnavn_engelsk":"Denmark","fagnavn_norsk":"Statsvitenskap","studietypenr":5303}
,{"avtale_eier":"Institutt for økonomi","utvprogramkode":"ERASMUS+","avtaleid":"881-6","eksternt_sted":"Turun yliopisto","landnavn_norsk":"Finland","landnavn_engelsk":"Finland","fagnavn_norsk":"Økonomi"}
,{"avtale_eier":"Universitetet i Bergen","utvprogramkode":"ERASMUS+","avtaleid":"841-28","eksternt_sted":"Örebro universitet","landnavn_norsk":"Sverige","landnavn_engelsk":"Sweden","fagnavn_norsk":"Alle fag","studietypenr":5297}
,{"avtale_eier":"Institutt for økonomi","utvprogramkode":"ERASMUS+","avtaleid":"127-3","eksternt_sted":"Örebro universitet","landnavn_norsk":"Sverige","landnavn_engelsk":"Sweden","fagnavn_norsk":"Økonomi"}
,{"avtale_eier":"Universitetet i Bergen","utvprogramkode":"BILATERAL","avtaleid":"1213-1","eksternt_sted":"City University of Hong Kong","landnavn_norsk":"Hong Kong","landnavn_engelsk":"Hong Kong","studietypenr":8392}
,{"avtale_eier":"Universitetet i Bergen","utvprogramkode":"NORDPLUS","avtaleid":"841-20","eksternt_sted":"Göteborgs universitet","landnavn_norsk":"Sverige","landnavn_engelsk":"Sweden","fagnavn_norsk":"Alle fag","studietypenr":5289}
,{"avtale_eier":"Institutt for sammenliknende politikk","utvprogramkode":"ERASMUS+","avtaleid":"1272","eksternt_sted":"İhsan Dogramaci Bilkent Üniversitesi ","landnavn_norsk":"Tyrkia","landnavn_engelsk":"Turkey","fagnavn_norsk":"Sammenliknende politikk","studietypenr":8219}
,{"avtale_eier":"Institutt for økonomi","utvprogramkode":"ERASMUS+","avtaleid":"134-5","eksternt_sted":"Åbo Akademi","landnavn_norsk":"Finland","landnavn_engelsk":"Finland","fagnavn_norsk":"Økonomi"}
,{"avtale_eier":"Institutt for geografi","utvprogramkode":"ERASMUS+","avtaleid":"346-6","eksternt_sted":"University of Southampton","landnavn_norsk":"Storbritannia og Nord-Irland","landnavn_engelsk":"United Kingdom","fagnavn_norsk":"Geografi","studietypenr":8372}
,{"avtale_eier":"Universitetet i Bergen","utvprogramkode":"ERASMUS+","avtaleid":"841-31","eksternt_sted":"Københavns Universitet","landnavn_norsk":"Danmark","landnavn_engelsk":"Denmark","fagnavn_norsk":"Alle fag","studietypenr":8228}
,{"avtale_eier":"Universitetet i Bergen","utvprogramkode":"ERASMUS+","avtaleid":"841-33","eksternt_sted":"Helsingin yliopisto \/ Helsingfors universitet","landnavn_norsk":"Finland","landnavn_engelsk":"Finland","fagnavn_norsk":"Alle fag","studietypenr":8223}
,{"avtale_eier":"Universitetet i Bergen","utvprogramkode":"ERASMUS+","avtaleid":"841-34","eksternt_sted":"Lunds universitet","landnavn_norsk":"Sverige","landnavn_engelsk":"Sweden","fagnavn_norsk":"Alle fag","studietypenr":8224}
,{"avtale_eier":"Universitetet i Bergen","utvprogramkode":"ERASMUS+","avtaleid":"841-35","eksternt_sted":"Stockholms universitet","landnavn_norsk":"Sverige","landnavn_engelsk":"Sweden","fagnavn_norsk":"Alle fag"}
,{"avtale_eier":"Institutt for informasjons- og medievitenskap","utvprogramkode":"ERASMUS+","avtaleid":"392-11","eksternt_sted":"Aarhus Universitet","landnavn_norsk":"Danmark","landnavn_engelsk":"Denmark","fagnavn_norsk":"Informasjonsvitenskap","studietypenr":8015}
,{"avtale_eier":"Universitetet i Bergen","utvprogramkode":"BILATERAL","avtaleid":"1321","eksternt_sted":"UCSC - University of California, Santa Cruz","landnavn_norsk":"USA","landnavn_engelsk":"USA","fagnavn_norsk":"Alle fag","studietypenr":8328}
,{"avtale_eier":"Institutt for økonomi","utvprogramkode":"ERASMUS+","avtaleid":"1328-1","eksternt_sted":"Tampereen yliopisto \/ Tammerfors universitet","landnavn_norsk":"Finland","landnavn_engelsk":"Finland","fagnavn_norsk":"Økonomi"}
,{"avtale_eier":"Institutt for administrasjon og organisasjonsvitenskap","utvprogramkode":"ERASMUS+","avtaleid":"1049","eksternt_sted":"Sciences Po Rennes","landnavn_norsk":"Frankrike","landnavn_engelsk":"France","fagnavn_norsk":"Sammenliknende politikk","studietypenr":8006}
,{"avtale_eier":"Institutt for økonomi","utvprogramkode":"ERASMUS+","avtaleid":"882-5","eksternt_sted":"Háskóli Íslands","landnavn_norsk":"Island","landnavn_engelsk":"Iceland","fagnavn_norsk":"Økonomi"}
,{"avtale_eier":"Institutt for informasjons- og medievitenskap","utvprogramkode":"ERASMUS+","avtaleid":"385-7","eksternt_sted":"Westfälische Wilhelms-Universität Münster","landnavn_norsk":"Tyskland","landnavn_engelsk":"Germany","fagnavn_norsk":"Kommunikasjon og informasjonsvitenskap","studietypenr":8014}
,{"avtale_eier":"Institutt for sammenliknende politikk","utvprogramkode":"NORDPLUS","avtaleid":"843-12","eksternt_sted":"Frodskaparsetur Føroya","landnavn_norsk":"Færøyene","landnavn_engelsk":"Faroe Islands","fagnavn_norsk":"Statsvitenskap","studietypenr":5312}
,{"avtale_eier":"Institutt for sammenliknende politikk","utvprogramkode":"ERASMUS+","avtaleid":"843-15","eksternt_sted":"Lunds universitet","landnavn_norsk":"Sverige","landnavn_engelsk":"Sweden","fagnavn_norsk":"Statsvitenskap","studietypenr":5315}
,{"avtale_eier":"Institutt for sammenliknende politikk","utvprogramkode":"ERASMUS+","avtaleid":"843-6","eksternt_sted":"Jyväskylän yliopisto","landnavn_norsk":"Finland","landnavn_engelsk":"Finland","fagnavn_norsk":"Statsvitenskap","studietypenr":5307}
,{"avtale_eier":"Universitetet i Bergen","utvprogramkode":"ERASMUS+","avtaleid":"841-9","eksternt_sted":"Jyväskylän yliopisto","landnavn_norsk":"Finland","landnavn_engelsk":"Finland","fagnavn_norsk":"Alle fag","studietypenr":5279}
,{"avtale_eier":"Institutt for sammenliknende politikk","utvprogramkode":"ERASMUS+","avtaleid":"843-9","eksternt_sted":"Turun yliopisto","landnavn_norsk":"Finland","landnavn_engelsk":"Finland","fagnavn_norsk":"Statsvitenskap","studietypenr":5310}
,{"avtale_eier":"Sosiologisk institutt","utvprogramkode":"ERASMUS+","avtaleid":"387-12","eksternt_sted":"Universität Potsdam","landnavn_norsk":"Tyskland","landnavn_engelsk":"Germany","fagnavn_norsk":"Sosiologi","studietypenr":8226}
,{"avtale_eier":"Institutt for geografi","utvprogramkode":"ERASMUS+","avtaleid":"781-3","eksternt_sted":"Université d'Avignon et des Pays de Vaucluse","landnavn_norsk":"Frankrike","landnavn_engelsk":"France","fagnavn_norsk":"Geografi","studietypenr":8371}
,{"avtale_eier":"Universitetet i Bergen","utvprogramkode":"BILATERAL","avtaleid":"801-4","eksternt_sted":"Renmin University of China ","landnavn_norsk":"Kina","landnavn_engelsk":"China","fagnavn_norsk":"Alle fag","studietypenr":8304}
,{"avtale_eier":"Institutt for informasjons- og medievitenskap","utvprogramkode":"ERASMUS+","avtaleid":"808-1","eksternt_sted":"Bath Spa University","landnavn_norsk":"Storbritannia og Nord-Irland","landnavn_engelsk":"United Kingdom","fagnavn_norsk":"Kommunikasjon og informasjonsvitenskap","studietypenr":7852}
,{"avtale_eier":"Institutt for sammenliknende politikk","utvprogramkode":"ERASMUS+","avtaleid":"879-2","eksternt_sted":"Europa-Universität Flensburg","landnavn_norsk":"Tyskland","landnavn_engelsk":"Germany","fagnavn_norsk":"Europastudier","studietypenr":8290}
,{"avtale_eier":"Institutt for informasjons- og medievitenskap","utvprogramkode":"ERASMUS+","avtaleid":"391-2","eksternt_sted":"Aalborg Universitet","landnavn_norsk":"Danmark","landnavn_engelsk":"Denmark","fagnavn_norsk":"Kommunikasjon og informasjonsvitenskap","studietypenr":7720}
,{"avtale_eier":"Institutt for økonomi","utvprogramkode":"ERASMUS+","avtaleid":"391-4","eksternt_sted":"Aalborg Universitet","landnavn_norsk":"Danmark","landnavn_engelsk":"Denmark","fagnavn_norsk":"Økonomi"}
,{"avtale_eier":"Universitetet i Bergen","utvprogramkode":"ERASMUS+","avtaleid":"251-1","eksternt_sted":"Università degli Studi di Padova","landnavn_norsk":"Italia","landnavn_engelsk":"Italy","fagnavn_norsk":"Alle fag","studietypenr":8322}
,{"avtale_eier":"Universitetet i Bergen","utvprogramkode":"ERASMUS+","avtaleid":"1319","eksternt_sted":"Université Jean Monnet Saint-Etienne","landnavn_norsk":"Frankrike","landnavn_engelsk":"France","fagnavn_norsk":"Alle fag","studietypenr":8325}
,{"avtale_eier":"Institutt for økonomi","utvprogramkode":"ERASMUS+","avtaleid":"736-1","eksternt_sted":"Universitat Pompeu Fabra","landnavn_norsk":"Spania","landnavn_engelsk":"Spain","fagnavn_norsk":"Samfunnsøkonomi","studietypenr":7841}
,{"avtale_eier":"Institutt for informasjons- og medievitenskap","utvprogramkode":"ERASMUS+","avtaleid":"169-5","eksternt_sted":"KU Leuven","landnavn_norsk":"Belgia","landnavn_engelsk":"Belgium","fagnavn_norsk":"Kommunikasjon og informasjonsvitenskap","studietypenr":7936}
,{"avtale_eier":"Institutt for informasjons- og medievitenskap","utvprogramkode":"ERASMUS+","avtaleid":"205-3","eksternt_sted":"Universitat de València","landnavn_norsk":"Spania","landnavn_engelsk":"Spain","fagnavn_norsk":"Journalistikk"}
,{"avtale_eier":"Universitetet i Bergen","utvprogramkode":"BILATERAL","avtaleid":"929-2","eksternt_sted":"Peking University","landnavn_norsk":"Kina","landnavn_engelsk":"China","fagnavn_norsk":"Alle fag","studietypenr":8303}
,{"avtale_eier":"Universitetet i Bergen","utvprogramkode":"BILATERAL","avtaleid":"1353","eksternt_sted":"Ewha Womans University","landnavn_norsk":"Sør-Korea","landnavn_engelsk":"South Korea","fagnavn_norsk":"Alle fag","studietypenr":9775}
,{"avtale_eier":"Institutt for økonomi","utvprogramkode":"ERASMUS+","avtaleid":"392-18","eksternt_sted":"Aarhus Universitet","landnavn_norsk":"Danmark","landnavn_engelsk":"Denmark","fagnavn_norsk":"Økonomi","studietypenr":9765}
,{"avtale_eier":"Institutt for geografi","utvprogramkode":"ERASMUS+ICM","avtaleid":"1312","eksternt_sted":"Lviv National University named after Ivan Franko","landnavn_norsk":"Ukraina","landnavn_engelsk":"Ukraine","fagnavn_norsk":"Økonomi"}
,{"avtale_eier":"Institutt for geografi","utvprogramkode":"ERASMUS+ICM","avtaleid":"981","eksternt_sted":"National University of \"Kyiv-Mohyla Academy\"","landnavn_norsk":"Ukraina","landnavn_engelsk":"Ukraine","fagnavn_norsk":"Økonomi"}
,{"avtale_eier":"Universitetet i Bergen","utvprogramkode":"BILATERAL","avtaleid":"958-68","eksternt_sted":"Kajaanin ammattikorkeakoulu","landnavn_norsk":"Finland","landnavn_engelsk":"Finland","studietypenr":8281}
,{"avtale_eier":"Institutt for geografi","utvprogramkode":"ERASMUS+","avtaleid":"114-8","eksternt_sted":"Radboud Universiteit","landnavn_norsk":"Nederland","landnavn_engelsk":"Netherlands","fagnavn_norsk":"Økonomi og administrasjon","studietypenr":7640}
,{"avtale_eier":"Institutt for sammenliknende politikk","utvprogramkode":"ERASMUS+","avtaleid":"293","eksternt_sted":"University College Dublin - National University of Ireland, Dublin","landnavn_norsk":"Irland","landnavn_engelsk":"Ireland","fagnavn_norsk":"Statsvitenskap"}
,{"avtale_eier":"Institutt for sosialantropologi","utvprogramkode":"ERASMUS+","avtaleid":"137-1","eksternt_sted":"University of Kent","landnavn_norsk":"Storbritannia og Nord-Irland","landnavn_engelsk":"United Kingdom","fagnavn_norsk":"Sosialantropologi","studietypenr":8237}
,{"avtale_eier":"Institutt for økonomi","utvprogramkode":"ERASMUS+","avtaleid":"114-9","eksternt_sted":"Radboud Universiteit","landnavn_norsk":"Nederland","landnavn_engelsk":"Netherlands","fagnavn_norsk":"Økonomi","studietypenr":8756}
,{"avtale_eier":"Institutt for informasjons- og medievitenskap","utvprogramkode":"ERASMUS+","avtaleid":"115-1","eksternt_sted":"Erasmus Universiteit Rotterdam","landnavn_norsk":"Nederland","landnavn_engelsk":"Netherlands","fagnavn_norsk":"Kommunikasjon og informasjonsvitenskap","studietypenr":8383}
,{"avtale_eier":"Institutt for sammenliknende politikk","utvprogramkode":"ERASMUS+","avtaleid":"293-1","eksternt_sted":"University College Dublin - National University of Ireland, Dublin","landnavn_norsk":"Irland","landnavn_engelsk":"Ireland","fagnavn_norsk":"Statsvitenskap","studietypenr":8753}
,{"avtale_eier":"Institutt for økonomi","utvprogramkode":"BILATERAL","avtaleid":"173-3","eksternt_sted":"Universität Bern","landnavn_norsk":"Sveits","landnavn_engelsk":"Switzerland","fagnavn_norsk":"Samfunnsøkonomi","studietypenr":7484}
,{"avtale_eier":"Universitetet i Bergen","utvprogramkode":"BILATERAL","avtaleid":"500-1","eksternt_sted":"Royal Melbourne Institute of Technology (RMIT University)","landnavn_norsk":"Australia","landnavn_engelsk":"Australia","fagnavn_norsk":"Alle fag"}
,{"avtale_eier":"Sosiologisk institutt","utvprogramkode":"ERASMUS+","avtaleid":"251-9","eksternt_sted":"Università degli Studi di Padova","landnavn_norsk":"Italia","landnavn_engelsk":"Italy","fagnavn_norsk":"Sosiologi","studietypenr":9766}
]
